{"type":"FeatureCollection","features":[]}{"type":"FeatureCollection","features":[{"type":"Feature","geometry":{"type":"Point","coordinates":[5.18583367960614,51.582220271910806]},"properties":{"location_id":33384,"base_color":"#B20A2F","provider_slug":"prorail","bands":["900"],"deleted":false,"is_kpn_huawei":null,"angles":[90.0,230.0]}},{"type":"Feature","geometry":{"type":"Point","coordinates":[5.834171393682066,52.19416873698376]},"properties":{"location_id":33540,"base_color":"#B20A2F","provider_slug":"prorail","bands":["900"],"deleted":false,"is_kpn_huawei":null,"angles":[265.0,45.0]}},{"type":"Feature","geometry":{"type":"Point","coordinates":[6.0733392720377255,52.511667540267844]},"properties":{"location_id":33618,"base_color":"#B20A2F","provider_slug":"prorail","bands":["900"],"deleted":false,"is_kpn_huawei":null,"angles":[125.0,310.0]}},{"type":"Feature","geometry":{"type":"Point","coordinates":[5.601667767364161,52.54860781034662]},"properties":{"location_id":43859,"base_color":"#B20A2F","provider_slug":"prorail","bands":["900"],"deleted":false,"is_kpn_huawei":null,"angles":[90.0,270.0]}},{"type":"Feature","geometry":{"type":"Point","coordinates":[3.701382917641948,51.482224342999665]},"properties":{"location_id":44940,"base_color":"#B20A2F","provider_slug":"prorail","bands":["900"],"deleted":false,"is_kpn_huawei":null,"angles":[150.0,220.0,30.0]}},{"type":"Feature","geometry":{"type":"Point","coordinates":[5.852501205840012,52.52471979250653]},"properties":{"location_id":46814,"base_color":"#B20A2F","provider_slug":"prorail","bands":["900"],"deleted":false,"is_kpn_huawei":null,"angles":[60.0,270.0]}},{"type":"Feature","geometry":{"type":"Point","coordinates":[5.5994439750856335,52.28861240070834]},"properties":{"location_id":33563,"base_color":"#B20A2F","provider_slug":"prorail","bands":["900"],"deleted":false,"is_kpn_huawei":null,"angles":[40.0,205.0]}},{"type":"Feature","geometry":{"type":"Point","coordinates":[4.2586183452096895,51.895829971242684]},"properties":{"location_id":33437,"base_color":"#B20A2F","provider_slug":"prorail","bands":["900"],"deleted":false,"is_kpn_huawei":null,"angles":[130.0,235.0]}},{"type":"Feature","geometry":{"type":"Point","coordinates":[4.314164548769422,51.889725544906746]},"properties":{"location_id":33434,"base_color":"#B20A2F","provider_slug":"prorail","bands":["900"],"deleted":false,"is_kpn_huawei":null,"angles":[100.0,255.0]}},{"type":"Feature","geometry":{"type":"Point","coordinates":[5.860003500616577,51.001385856822225]},"properties":{"location_id":33343,"base_color":"#B20A2F","provider_slug":"prorail","bands":["900"],"deleted":false,"is_kpn_huawei":null,"angles":[340.0,205.0]}},{"type":"Feature","geometry":{"type":"Point","coordinates":[5.960558119198618,50.89527541536045]},"properties":{"location_id":33335,"base_color":"#B20A2F","provider_slug":"prorail","bands":["900"],"deleted":false,"is_kpn_huawei":null,"angles":[300.0,110.0,255.0]}},{"type":"Feature","geometry":{"type":"Point","coordinates":[6.736664317134592,52.661390708957505]},"properties":{"location_id":33631,"base_color":"#B20A2F","provider_slug":"prorail","bands":["900"],"deleted":false,"is_kpn_huawei":null,"angles":[200.0,20.0]}},{"type":"Feature","geometry":{"type":"Point","coordinates":[5.219998431889385,52.215830191074936]},"properties":{"location_id":33548,"base_color":"#B20A2F","provider_slug":"prorail","bands":["900"],"deleted":false,"is_kpn_huawei":null,"angles":[105.0,285.0]}},{"type":"Feature","geometry":{"type":"Point","coordinates":[5.623882046475941,52.34194390682452]},"properties":{"location_id":54605,"base_color":"#B20A2F","provider_slug":"prorail","bands":["900"],"deleted":false,"is_kpn_huawei":null,"angles":[210.0,90.0]}},{"type":"Feature","geometry":{"type":"Point","coordinates":[5.279451735715496,52.69305853604225]},"properties":{"location_id":33635,"base_color":"#B20A2F","provider_slug":"prorail","bands":["900"],"deleted":false,"is_kpn_huawei":null,"angles":[0.0,275.0]}},{"type":"Feature","geometry":{"type":"Point","coordinates":[4.821673331477003,52.06555343860346]},"properties":{"location_id":33503,"base_color":"#B20A2F","provider_slug":"prorail","bands":["900"],"deleted":false,"is_kpn_huawei":null,"angles":[65.0,180.0,300.0]}},{"type":"Feature","geometry":{"type":"Point","coordinates":[4.634445459428894,52.45444528257703]},"properties":{"location_id":33604,"base_color":"#B20A2F","provider_slug":"prorail","bands":["900"],"deleted":false,"is_kpn_huawei":null,"angles":[185.0,100.0,300.0]}},{"type":"Feature","geometry":{"type":"Point","coordinates":[6.572772872710296,52.50888607985729]},"properties":{"location_id":33615,"base_color":"#B20A2F","provider_slug":"prorail","bands":["900"],"deleted":false,"is_kpn_huawei":null,"angles":[50.0,260.0,190.0]}},{"type":"Feature","geometry":{"type":"Point","coordinates":[4.80972788247919,52.85694009718576]},"properties":{"location_id":56133,"base_color":"#B20A2F","provider_slug":"prorail","bands":["900"],"deleted":false,"is_kpn_huawei":null,"angles":[0.0,190.0]}},{"type":"Feature","geometry":{"type":"Point","coordinates":[4.359165426873232,51.87721987122787]},"properties":{"location_id":33432,"base_color":"#B20A2F","provider_slug":"prorail","bands":["900"],"deleted":false,"is_kpn_huawei":null,"angles":[80.0,285.0]}},{"type":"Feature","geometry":{"type":"Point","coordinates":[4.586113088408866,52.12194670918044]},"properties":{"location_id":38578,"base_color":"#B20A2F","provider_slug":"prorail","bands":["900"],"deleted":false,"is_kpn_huawei":null,"angles":[290.0,70.0]}},{"type":"Feature","geometry":{"type":"Point","coordinates":[4.690838069932966,51.84638754253872]},"properties":{"location_id":33421,"base_color":"#B20A2F","provider_slug":"prorail","bands":["900"],"deleted":false,"is_kpn_huawei":null,"angles":[-1.0]}},{"type":"Feature","geometry":{"type":"Point","coordinates":[6.287773044130567,52.25333730394442]},"properties":{"location_id":59622,"base_color":"#B20A2F","provider_slug":"prorail","bands":["900"],"deleted":false,"is_kpn_huawei":null,"angles":[80.0,265.0]}},{"type":"Feature","geometry":{"type":"Point","coordinates":[4.64333944729315,52.25694689190566]},"properties":{"location_id":59623,"base_color":"#B20A2F","provider_slug":"prorail","bands":["900"],"deleted":false,"is_kpn_huawei":null,"angles":[40.0,195.0,230.0]}},{"type":"Feature","geometry":{"type":"Point","coordinates":[6.7124930612531895,52.25972637313545]},"properties":{"location_id":59624,"base_color":"#B20A2F","provider_slug":"prorail","bands":["900"],"deleted":false,"is_kpn_huawei":null,"angles":[90.0,245.0]}},{"type":"Feature","geometry":{"type":"Point","coordinates":[6.791668999362953,52.262496995818424]},"properties":{"location_id":59625,"base_color":"#B20A2F","provider_slug":"prorail","bands":["900"],"deleted":false,"is_kpn_huawei":null,"angles":[265.0,315.0,100.0]}},{"type":"Feature","geometry":{"type":"Point","coordinates":[6.14499669173778,52.27583014038277]},"properties":{"location_id":59626,"base_color":"#B20A2F","provider_slug":"prorail","bands":["900"],"deleted":false,"is_kpn_huawei":null,"angles":[160.0,345.0]}},{"type":"Feature","geometry":{"type":"Point","coordinates":[6.856661176655892,52.28527563991072]},"properties":{"location_id":59627,"base_color":"#B20A2F","provider_slug":"prorail","bands":["900"],"deleted":false,"is_kpn_huawei":null,"angles":[65.0,230.0]}},{"type":"Feature","geometry":{"type":"Point","coordinates":[5.15027964290713,52.28916830689613]},"properties":{"location_id":59628,"base_color":"#B20A2F","provider_slug":"prorail","bands":["900"],"deleted":false,"is_kpn_huawei":null,"angles":[160.0,270.0]}},{"type":"Feature","geometry":{"type":"Point","coordinates":[6.419717259878279,52.29249855416959]},"properties":{"location_id":59629,"base_color":"#B20A2F","provider_slug":"prorail","bands":["900"],"deleted":false,"is_kpn_huawei":null,"angles":[90.0,235.0]}},{"type":"Feature","geometry":{"type":"Point","coordinates":[4.702784002360396,52.29444459133363]},"properties":{"location_id":59630,"base_color":"#B20A2F","provider_slug":"prorail","bands":["900"],"deleted":false,"is_kpn_huawei":null,"angles":[80.0,230.0]}},{"type":"Feature","geometry":{"type":"Point","coordinates":[6.748895434670562,52.2994475117939]},"properties":{"location_id":33568,"base_color":"#B20A2F","provider_slug":"prorail","bands":["900"],"deleted":false,"is_kpn_huawei":null,"angles":[145.0,310.0]}},{"type":"Feature","geometry":{"type":"Point","coordinates":[4.578326542682927,52.300273925779855]},"properties":{"location_id":59631,"base_color":"#B20A2F","provider_slug":"prorail","bands":["900"],"deleted":false,"is_kpn_huawei":null,"angles":[20.0,215.0]}},{"type":"Feature","geometry":{"type":"Point","coordinates":[6.93555580176306,52.30611183918677]},"properties":{"location_id":59632,"base_color":"#B20A2F","provider_slug":"prorail","bands":["900"],"deleted":false,"is_kpn_huawei":null,"angles":[250.0,85.0]}},{"type":"Feature","geometry":{"type":"Point","coordinates":[4.9552779136130995,52.30666441971962]},"properties":{"location_id":59633,"base_color":"#B20A2F","provider_slug":"prorail","bands":["900"],"deleted":false,"is_kpn_huawei":null,"angles":[325.0,150.0]}},{"type":"Feature","geometry":{"type":"Point","coordinates":[7.0108371869905115,52.308328936683665]},"properties":{"location_id":59634,"base_color":"#B20A2F","provider_slug":"prorail","bands":["900"],"deleted":false,"is_kpn_huawei":null,"angles":[260.0,85.0]}},{"type":"Feature","geometry":{"type":"Point","coordinates":[6.519169652009349,52.309447950998674]},"properties":{"location_id":33572,"base_color":"#B20A2F","provider_slug":"prorail","bands":["900"],"deleted":false,"is_kpn_huawei":null,"angles":[250.0,35.0]}},{"type":"Feature","geometry":{"type":"Point","coordinates":[4.763607851293258,52.310833421332305]},"properties":{"location_id":59635,"base_color":"#B20A2F","provider_slug":"prorail","bands":["900"],"deleted":false,"is_kpn_huawei":null,"angles":[-1.0]}},{"type":"Feature","geometry":{"type":"Point","coordinates":[5.076941946211464,52.31166577699779]},"properties":{"location_id":54604,"base_color":"#B20A2F","provider_slug":"prorail","bands":["900"],"deleted":false,"is_kpn_huawei":null,"angles":[280.0,140.0,60.0]}},{"type":"Feature","geometry":{"type":"Point","coordinates":[4.95443915422591,52.32805225461352]},"properties":{"location_id":59636,"base_color":"#B20A2F","provider_slug":"prorail","bands":["900"],"deleted":false,"is_kpn_huawei":null,"angles":[170.0,90.0,250.0,30.0]}},{"type":"Feature","geometry":{"type":"Point","coordinates":[4.888611823602889,52.33500138892366]},"properties":{"location_id":33575,"base_color":"#B20A2F","provider_slug":"prorail","bands":["900"],"deleted":false,"is_kpn_huawei":null,"angles":[0.0,100.0,300.0]}},{"type":"Feature","geometry":{"type":"Point","coordinates":[6.123337325652754,52.33583617300584]},"properties":{"location_id":59637,"base_color":"#B20A2F","provider_slug":"prorail","bands":["900"],"deleted":false,"is_kpn_huawei":null,"angles":[345.0,175.0]}},{"type":"Feature","geometry":{"type":"Point","coordinates":[4.809449415570157,52.33777810667223]},"properties":{"location_id":59638,"base_color":"#B20A2F","provider_slug":"prorail","bands":["900"],"deleted":false,"is_kpn_huawei":null,"angles":[70.0,230.0]}},{"type":"Feature","geometry":{"type":"Point","coordinates":[5.236117518052434,52.35138689640862]},"properties":{"location_id":59639,"base_color":"#B20A2F","provider_slug":"prorail","bands":["900"],"deleted":false,"is_kpn_huawei":null,"angles":[0.0,260.0]}},{"type":"Feature","geometry":{"type":"Point","coordinates":[4.607494660270932,52.35999738623111]},"properties":{"location_id":59640,"base_color":"#B20A2F","provider_slug":"prorail","bands":["900"],"deleted":false,"is_kpn_huawei":null,"angles":[205.0,15.0]}},{"type":"Feature","geometry":{"type":"Point","coordinates":[4.931394110354535,52.36083388353525]},"properties":{"location_id":59641,"base_color":"#B20A2F","provider_slug":"prorail","bands":["900"],"deleted":false,"is_kpn_huawei":null,"angles":[0.0,225.0,125.0]}},{"type":"Feature","geometry":{"type":"Point","coordinates":[6.580558715465336,52.361948156438146]},"properties":{"location_id":59642,"base_color":"#B20A2F","provider_slug":"prorail","bands":["900"],"deleted":false,"is_kpn_huawei":null,"angles":[80.0,275.0,205.0]}},{"type":"Feature","geometry":{"type":"Point","coordinates":[5.767500202068739,52.36278016315768]},"properties":{"location_id":59643,"base_color":"#B20A2F","provider_slug":"prorail","bands":["900"],"deleted":false,"is_kpn_huawei":null,"angles":[60.0,245.0]}},{"type":"Feature","geometry":{"type":"Point","coordinates":[6.436945943660952,52.36527786033613]},"properties":{"location_id":59644,"base_color":"#B20A2F","provider_slug":"prorail","bands":["900"],"deleted":false,"is_kpn_huawei":null,"angles":[280.0]}},{"type":"Feature","geometry":{"type":"Point","coordinates":[6.6522222817560825,52.36555411357235]},"properties":{"location_id":59645,"base_color":"#B20A2F","provider_slug":"prorail","bands":["900"],"deleted":false,"is_kpn_huawei":null,"angles":[155.0,260.0,310.0]}},{"type":"Feature","geometry":{"type":"Point","coordinates":[6.460553466793351,52.3663873446215]},"properties":{"location_id":59646,"base_color":"#B20A2F","provider_slug":"prorail","bands":["900"],"deleted":false,"is_kpn_huawei":null,"angles":[275.0,95.0]}},{"type":"Feature","geometry":{"type":"Point","coordinates":[4.525831399959387,52.373335723871186]},"properties":{"location_id":59647,"base_color":"#B20A2F","provider_slug":"prorail","bands":["900"],"deleted":false,"is_kpn_huawei":null,"angles":[75.0]}},{"type":"Feature","geometry":{"type":"Point","coordinates":[4.9008339079307035,52.3791640430075]},"properties":{"location_id":59648,"base_color":"#B20A2F","provider_slug":"prorail","bands":["900"],"deleted":false,"is_kpn_huawei":null,"angles":[-1.0]}},{"type":"Feature","geometry":{"type":"Point","coordinates":[4.895551510253675,52.38138915417674]},"properties":{"location_id":33589,"base_color":"#B20A2F","provider_slug":"prorail","bands":["900"],"deleted":false,"is_kpn_huawei":null,"angles":[120.0,300.0]}},{"type":"Feature","geometry":{"type":"Point","coordinates":[6.277506914788437,52.38722142033079]},"properties":{"location_id":59650,"base_color":"#B20A2F","provider_slug":"prorail","bands":["900"],"deleted":false,"is_kpn_huawei":null,"angles":[105.0,305.0]}},{"type":"Feature","geometry":{"type":"Point","coordinates":[4.837777794301062,52.389170219237116]},"properties":{"location_id":59652,"base_color":"#B20A2F","provider_slug":"prorail","bands":["900"],"deleted":false,"is_kpn_huawei":null,"angles":[280.0,90.0,180.0]}},{"type":"Feature","geometry":{"type":"Point","coordinates":[4.600272654128233,52.392225238447075]},"properties":{"location_id":59653,"base_color":"#B20A2F","provider_slug":"prorail","bands":["900"],"deleted":false,"is_kpn_huawei":null,"angles":[235.0,110.0]}},{"type":"Feature","geometry":{"type":"Point","coordinates":[5.85666490815338,52.392496777965654]},"properties":{"location_id":59654,"base_color":"#B20A2F","provider_slug":"prorail","bands":["900"],"deleted":false,"is_kpn_huawei":null,"angles":[240.0,55.0]}},{"type":"Feature","geometry":{"type":"Point","coordinates":[4.803334237544469,52.40333185198444]},"properties":{"location_id":59655,"base_color":"#B20A2F","provider_slug":"prorail","bands":["900"],"deleted":false,"is_kpn_huawei":null,"angles":[10.0,250.0,150.0]}},{"type":"Feature","geometry":{"type":"Point","coordinates":[4.8405524387022085,52.403608313897124]},"properties":{"location_id":59656,"base_color":"#B20A2F","provider_slug":"prorail","bands":["900"],"deleted":false,"is_kpn_huawei":null,"angles":[180.0,60.0,300.0]}},{"type":"Feature","geometry":{"type":"Point","coordinates":[4.759994564121775,52.40471910748752]},"properties":{"location_id":59657,"base_color":"#B20A2F","provider_slug":"prorail","bands":["900"],"deleted":false,"is_kpn_huawei":null,"angles":[0.0,120.0]}},{"type":"Feature","geometry":{"type":"Point","coordinates":[4.629996965220822,52.40833651497341]},"properties":{"location_id":59658,"base_color":"#B20A2F","provider_slug":"prorail","bands":["900"],"deleted":false,"is_kpn_huawei":null,"angles":[200.0,5.0]}},{"type":"Feature","geometry":{"type":"Point","coordinates":[5.372226974834108,52.41499718303802]},"properties":{"location_id":59659,"base_color":"#B20A2F","provider_slug":"prorail","bands":["900"],"deleted":false,"is_kpn_huawei":null,"angles":[265.0,35.0]}},{"type":"Feature","geometry":{"type":"Point","coordinates":[4.814715340909736,52.42777996404923]},"properties":{"location_id":59660,"base_color":"#B20A2F","provider_slug":"prorail","bands":["900"],"deleted":false,"is_kpn_huawei":null,"angles":[-1.0]}},{"type":"Feature","geometry":{"type":"Point","coordinates":[4.816939405227268,52.43889042842874]},"properties":{"location_id":59661,"base_color":"#B20A2F","provider_slug":"prorail","bands":["900"],"deleted":false,"is_kpn_huawei":null,"angles":[300.0,190.0]}},{"type":"Feature","geometry":{"type":"Point","coordinates":[5.993053670352185,52.45027929160491]},"properties":{"location_id":59662,"base_color":"#B20A2F","provider_slug":"prorail","bands":["900"],"deleted":false,"is_kpn_huawei":null,"angles":[235.0,45.0]}},{"type":"Feature","geometry":{"type":"Point","coordinates":[6.568613969950813,52.45694885520444]},"properties":{"location_id":59663,"base_color":"#B20A2F","provider_slug":"prorail","bands":["900"],"deleted":false,"is_kpn_huawei":null,"angles":[160.0,350.0]}},{"type":"Feature","geometry":{"type":"Point","coordinates":[4.832229197953279,52.458052679148196]},"properties":{"location_id":59664,"base_color":"#B20A2F","provider_slug":"prorail","bands":["900"],"deleted":false,"is_kpn_huawei":null,"angles":[300.0,55.0]}},{"type":"Feature","geometry":{"type":"Point","coordinates":[4.655007143658847,52.458330933664605]},"properties":{"location_id":59665,"base_color":"#B20A2F","provider_slug":"prorail","bands":["900"],"deleted":false,"is_kpn_huawei":null,"angles":[-1.0]}},{"type":"Feature","geometry":{"type":"Point","coordinates":[4.671659681253296,52.48305886712958]},"properties":{"location_id":59666,"base_color":"#B20A2F","provider_slug":"prorail","bands":["900"],"deleted":false,"is_kpn_huawei":null,"angles":[35.0,235.0]}},{"type":"Feature","geometry":{"type":"Point","coordinates":[6.046660596822875,52.486941248595166]},"properties":{"location_id":59667,"base_color":"#B20A2F","provider_slug":"prorail","bands":["900"],"deleted":false,"is_kpn_huawei":null,"angles":[225.0,290.0,70.0]}},{"type":"Feature","geometry":{"type":"Point","coordinates":[6.14304900387309,52.4886128302475]},"properties":{"location_id":33610,"base_color":"#B20A2F","provider_slug":"prorail","bands":["900"],"deleted":false,"is_kpn_huawei":null,"angles":[70.0,185.0,140.0,30.0]}},{"type":"Feature","geometry":{"type":"Point","coordinates":[4.771116918024552,52.49361137269229]},"properties":{"location_id":59668,"base_color":"#B20A2F","provider_slug":"prorail","bands":["900"],"deleted":false,"is_kpn_huawei":null,"angles":[120.0,290.0]}},{"type":"Feature","geometry":{"type":"Point","coordinates":[5.476113363802838,52.49499752382455]},"properties":{"location_id":59669,"base_color":"#B20A2F","provider_slug":"prorail","bands":["900"],"deleted":false,"is_kpn_huawei":null,"angles":[355.0,220.0]}},{"type":"Feature","geometry":{"type":"Point","coordinates":[6.076672468835424,52.49778034264311]},"properties":{"location_id":59670,"base_color":"#B20A2F","provider_slug":"prorail","bands":["900"],"deleted":false,"is_kpn_huawei":null,"angles":[210.0,10.0]}},{"type":"Feature","geometry":{"type":"Point","coordinates":[6.323060076415678,52.50194279778956]},"properties":{"location_id":59671,"base_color":"#B20A2F","provider_slug":"prorail","bands":["900"],"deleted":false,"is_kpn_huawei":null,"angles":[80.0,260.0]}},{"type":"Feature","geometry":{"type":"Point","coordinates":[6.442775836236316,52.50833470005171]},"properties":{"location_id":59672,"base_color":"#B20A2F","provider_slug":"prorail","bands":["900"],"deleted":false,"is_kpn_huawei":null,"angles":[85.0,270.0]}},{"type":"Feature","geometry":{"type":"Point","coordinates":[4.969996797546792,52.511391802298775]},"properties":{"location_id":59673,"base_color":"#B20A2F","provider_slug":"prorail","bands":["900"],"deleted":false,"is_kpn_huawei":null,"angles":[45.0,230.0]}},{"type":"Feature","geometry":{"type":"Point","coordinates":[5.943881650178877,52.51139316189314]},"properties":{"location_id":59674,"base_color":"#B20A2F","provider_slug":"prorail","bands":["900"],"deleted":false,"is_kpn_huawei":null,"angles":[105.0,310.0]}},{"type":"Feature","geometry":{"type":"Point","coordinates":[4.70138838877751,52.522501306718816]},"properties":{"location_id":59675,"base_color":"#B20A2F","provider_slug":"prorail","bands":["900"],"deleted":false,"is_kpn_huawei":null,"angles":[310.0,130.0,190.0]}},{"type":"Feature","geometry":{"type":"Point","coordinates":[5.727501908123937,52.53388895931349]},"properties":{"location_id":59676,"base_color":"#B20A2F","provider_slug":"prorail","bands":["900"],"deleted":false,"is_kpn_huawei":null,"angles":[290.0,100.0]}},{"type":"Feature","geometry":{"type":"Point","coordinates":[5.488060142615885,52.542225135698416]},"properties":{"location_id":59677,"base_color":"#B20A2F","provider_slug":"prorail","bands":["900"],"deleted":false,"is_kpn_huawei":null,"angles":[210.0,60.0]}},{"type":"Feature","geometry":{"type":"Point","coordinates":[5.925559714165627,52.55027649790383]},"properties":{"location_id":33624,"base_color":"#B20A2F","provider_slug":"prorail","bands":["900"],"deleted":false,"is_kpn_huawei":null,"angles":[90.0]}},{"type":"Feature","geometry":{"type":"Point","coordinates":[6.633608227392794,52.55833552114491]},"properties":{"location_id":59678,"base_color":"#B20A2F","provider_slug":"prorail","bands":["900"],"deleted":false,"is_kpn_huawei":null,"angles":[205.0,15.0]}},{"type":"Feature","geometry":{"type":"Point","coordinates":[4.665277603209904,52.561940196538096]},"properties":{"location_id":33626,"base_color":"#B20A2F","provider_slug":"prorail","bands":["900"],"deleted":false,"is_kpn_huawei":null,"angles":[210.0,30.0]}},{"type":"Feature","geometry":{"type":"Point","coordinates":[4.996666094487114,52.578887453858954]},"properties":{"location_id":59679,"base_color":"#B20A2F","provider_slug":"prorail","bands":["900"],"deleted":false,"is_kpn_huawei":null,"angles":[175.0,15.0]}},{"type":"Feature","geometry":{"type":"Point","coordinates":[6.238334227516064,52.59000415269668]},"properties":{"location_id":59680,"base_color":"#B20A2F","provider_slug":"prorail","bands":["900"],"deleted":false,"is_kpn_huawei":null,"angles":[210.0,350.0]}},{"type":"Feature","geometry":{"type":"Point","coordinates":[4.74111340487878,52.64222069890552]},"properties":{"location_id":59681,"base_color":"#B20A2F","provider_slug":"prorail","bands":["900"],"deleted":false,"is_kpn_huawei":null,"angles":[210.0,75.0]}},{"type":"Feature","geometry":{"type":"Point","coordinates":[5.031941953162369,52.64278008240117]},"properties":{"location_id":59682,"base_color":"#B20A2F","provider_slug":"prorail","bands":["900"],"deleted":false,"is_kpn_huawei":null,"angles":[75.0,230.0,295.0]}},{"type":"Feature","geometry":{"type":"Point","coordinates":[4.90917342516702,52.67611460601593]},"properties":{"location_id":59683,"base_color":"#B20A2F","provider_slug":"prorail","bands":["900"],"deleted":false,"is_kpn_huawei":null,"angles":[0.0,105.0,275.0]}},{"type":"Feature","geometry":{"type":"Point","coordinates":[4.838326318922731,52.67917006462192]},"properties":{"location_id":59684,"base_color":"#B20A2F","provider_slug":"prorail","bands":["900"],"deleted":false,"is_kpn_huawei":null,"angles":[0.0,90.0,230.0]}},{"type":"Feature","geometry":{"type":"Point","coordinates":[5.138895172268763,52.67917025601423]},"properties":{"location_id":59685,"base_color":"#B20A2F","provider_slug":"prorail","bands":["900"],"deleted":false,"is_kpn_huawei":null,"angles":[235.0,70.0]}},{"type":"Feature","geometry":{"type":"Point","coordinates":[6.189166733611555,52.69472613645121]},"properties":{"location_id":59686,"base_color":"#B20A2F","provider_slug":"prorail","bands":["900"],"deleted":false,"is_kpn_huawei":null,"angles":[0.0,165.0,70.0]}},{"type":"Feature","geometry":{"type":"Point","coordinates":[6.318606817712422,52.69638941609494]},"properties":{"location_id":59687,"base_color":"#B20A2F","provider_slug":"prorail","bands":["900"],"deleted":false,"is_kpn_huawei":null,"angles":[280.0,60.0]}},{"type":"Feature","geometry":{"type":"Point","coordinates":[6.848056752359286,52.71805707073335]},"properties":{"location_id":59688,"base_color":"#B20A2F","provider_slug":"prorail","bands":["900"],"deleted":false,"is_kpn_huawei":null,"angles":[20.0,230.0]}},{"type":"Feature","geometry":{"type":"Point","coordinates":[6.473614686684833,52.73777471745286]},"properties":{"location_id":59689,"base_color":"#B20A2F","provider_slug":"prorail","bands":["900"],"deleted":false,"is_kpn_huawei":null,"angles":[240.0,15.0]}},{"type":"Feature","geometry":{"type":"Point","coordinates":[6.903059565571213,52.779720085935885]},"properties":{"location_id":59690,"base_color":"#B20A2F","provider_slug":"prorail","bands":["900"],"deleted":false,"is_kpn_huawei":null,"angles":[200.0,350.0]}},{"type":"Feature","geometry":{"type":"Point","coordinates":[4.80611805185966,52.78222414580843]},"properties":{"location_id":59691,"base_color":"#B20A2F","provider_slug":"prorail","bands":["900"],"deleted":false,"is_kpn_huawei":null,"angles":[0.0,165.0]}},{"type":"Feature","geometry":{"type":"Point","coordinates":[6.124440436475698,52.787496622737265]},"properties":{"location_id":33642,"base_color":"#B20A2F","provider_slug":"prorail","bands":["900"],"deleted":false,"is_kpn_huawei":null,"angles":[125.0,310.0]}},{"type":"Feature","geometry":{"type":"Point","coordinates":[6.501389061877497,52.801113442362364]},"properties":{"location_id":59692,"base_color":"#B20A2F","provider_slug":"prorail","bands":["900"],"deleted":false,"is_kpn_huawei":null,"angles":[10.0,190.0]}},{"type":"Feature","geometry":{"type":"Point","coordinates":[6.046385683153709,52.845002818979765]},"properties":{"location_id":33643,"base_color":"#B20A2F","provider_slug":"prorail","bands":["900"],"deleted":false,"is_kpn_huawei":null,"angles":[145.0,325.0]}},{"type":"Feature","geometry":{"type":"Point","coordinates":[6.542217189871149,52.91361455913248]},"properties":{"location_id":59693,"base_color":"#B20A2F","provider_slug":"prorail","bands":["900"],"deleted":false,"is_kpn_huawei":null,"angles":[10.0,190.0]}},{"type":"Feature","geometry":{"type":"Point","coordinates":[4.767226961330501,52.9308308613051]},"properties":{"location_id":59694,"base_color":"#B20A2F","provider_slug":"prorail","bands":["900"],"deleted":false,"is_kpn_huawei":null,"angles":[345.0,155.0]}},{"type":"Feature","geometry":{"type":"Point","coordinates":[5.930280252323504,52.94499793671384]},"properties":{"location_id":59695,"base_color":"#B20A2F","provider_slug":"prorail","bands":["900"],"deleted":false,"is_kpn_huawei":null,"angles":[330.0,140.0]}},{"type":"Feature","geometry":{"type":"Point","coordinates":[5.423611142096354,52.94694628583356]},"properties":{"location_id":59696,"base_color":"#B20A2F","provider_slug":"prorail","bands":["900"],"deleted":false,"is_kpn_huawei":null,"angles":[200.0,35.0]}},{"type":"Feature","geometry":{"type":"Point","coordinates":[5.555281833953997,52.99110869109451]},"properties":{"location_id":59697,"base_color":"#B20A2F","provider_slug":"prorail","bands":["900"],"deleted":false,"is_kpn_huawei":null,"angles":[275.0,60.0]}},{"type":"Feature","geometry":{"type":"Point","coordinates":[6.589159838569944,53.00555694111805]},"properties":{"location_id":59698,"base_color":"#B20A2F","provider_slug":"prorail","bands":["900"],"deleted":false,"is_kpn_huawei":null,"angles":[35.0,215.0]}},{"type":"Feature","geometry":{"type":"Point","coordinates":[5.651659444204969,53.03666479046103]},"properties":{"location_id":59699,"base_color":"#B20A2F","provider_slug":"prorail","bands":["900"],"deleted":false,"is_kpn_huawei":null,"angles":[25.0,220.0]}},{"type":"Feature","geometry":{"type":"Point","coordinates":[6.630279688526221,53.08111242697034]},"properties":{"location_id":59700,"base_color":"#B20A2F","provider_slug":"prorail","bands":["900"],"deleted":false,"is_kpn_huawei":null,"angles":[355.0,190.0]}},{"type":"Feature","geometry":{"type":"Point","coordinates":[5.821669577327722,53.09166614219551]},"properties":{"location_id":59701,"base_color":"#B20A2F","provider_slug":"prorail","bands":["900"],"deleted":false,"is_kpn_huawei":null,"angles":[160.0,345.0]}},{"type":"Feature","geometry":{"type":"Point","coordinates":[5.717227366438241,53.12527449590408]},"properties":{"location_id":59702,"base_color":"#B20A2F","provider_slug":"prorail","bands":["900"],"deleted":false,"is_kpn_huawei":null,"angles":[0.0,215.0]}},{"type":"Feature","geometry":{"type":"Point","coordinates":[7.047225632661019,53.13666856349622]},"properties":{"location_id":59703,"base_color":"#B20A2F","provider_slug":"prorail","bands":["900"],"deleted":false,"is_kpn_huawei":null,"angles":[60.0,295.0]}},{"type":"Feature","geometry":{"type":"Point","coordinates":[6.777504813444272,53.15999871898774]},"properties":{"location_id":59704,"base_color":"#B20A2F","provider_slug":"prorail","bands":["900"],"deleted":false,"is_kpn_huawei":null,"angles":[275.0,95.0]}},{"type":"Feature","geometry":{"type":"Point","coordinates":[6.883051372456962,53.16250262102844]},"properties":{"location_id":59705,"base_color":"#B20A2F","provider_slug":"prorail","bands":["900"],"deleted":false,"is_kpn_huawei":null,"angles":[80.0,180.0,255.0]}},{"type":"Feature","geometry":{"type":"Point","coordinates":[6.980550839229153,53.16416714282694]},"properties":{"location_id":59706,"base_color":"#B20A2F","provider_slug":"prorail","bands":["900"],"deleted":false,"is_kpn_huawei":null,"angles":[130.0,290.0]}},{"type":"Feature","geometry":{"type":"Point","coordinates":[6.625277487327375,53.164723086619546]},"properties":{"location_id":59707,"base_color":"#B20A2F","provider_slug":"prorail","bands":["900"],"deleted":false,"is_kpn_huawei":null,"angles":[340.0,165.0]}},{"type":"Feature","geometry":{"type":"Point","coordinates":[5.433056988103507,53.17110755055462]},"properties":{"location_id":59708,"base_color":"#B20A2F","provider_slug":"prorail","bands":["900"],"deleted":false,"is_kpn_huawei":null,"angles":[80.0,270.0]}},{"type":"Feature","geometry":{"type":"Point","coordinates":[5.608616319498412,53.173337829313915]},"properties":{"location_id":33660,"base_color":"#B20A2F","provider_slug":"prorail","bands":["900"],"deleted":false,"is_kpn_huawei":null,"angles":[280.0,75.0]}},{"type":"Feature","geometry":{"type":"Point","coordinates":[7.174727994716799,53.173337417664676]},"properties":{"location_id":59709,"base_color":"#B20A2F","provider_slug":"prorail","bands":["900"],"deleted":false,"is_kpn_huawei":null,"angles":[250.0,67.0]}},{"type":"Feature","geometry":{"type":"Point","coordinates":[6.6433315554563706,53.184997834802076]},"properties":{"location_id":59710,"base_color":"#B20A2F","provider_slug":"prorail","bands":["900"],"deleted":false,"is_kpn_huawei":null,"angles":[115.0,300.0]}},{"type":"Feature","geometry":{"type":"Point","coordinates":[5.764996709608975,53.19333554904236]},"properties":{"location_id":59711,"base_color":"#B20A2F","provider_slug":"prorail","bands":["900"],"deleted":false,"is_kpn_huawei":null,"angles":[80.0,155.0,260.0,205.0]}},{"type":"Feature","geometry":{"type":"Point","coordinates":[6.551668194980377,53.21055474820249]},"properties":{"location_id":33664,"base_color":"#B20A2F","provider_slug":"prorail","bands":["900"],"deleted":false,"is_kpn_huawei":null,"angles":[345.0,90.0,270.0]}},{"type":"Feature","geometry":{"type":"Point","coordinates":[6.489160808346337,53.2130592310723]},"properties":{"location_id":59712,"base_color":"#B20A2F","provider_slug":"prorail","bands":["900"],"deleted":false,"is_kpn_huawei":null,"angles":[305.0,100.0]}},{"type":"Feature","geometry":{"type":"Point","coordinates":[5.933894399598702,53.21860844165625]},"properties":{"location_id":59713,"base_color":"#B20A2F","provider_slug":"prorail","bands":["900"],"deleted":false,"is_kpn_huawei":null,"angles":[60.0,245.0]}},{"type":"Feature","geometry":{"type":"Point","coordinates":[6.55832594828643,53.23860825284653]},"properties":{"location_id":59714,"base_color":"#B20A2F","provider_slug":"prorail","bands":["900"],"deleted":false,"is_kpn_huawei":null,"angles":[345.0,185.0]}},{"type":"Feature","geometry":{"type":"Point","coordinates":[6.03250640309683,53.25055713500576]},"properties":{"location_id":59715,"base_color":"#B20A2F","provider_slug":"prorail","bands":["900"],"deleted":false,"is_kpn_huawei":null,"angles":[90.0,235.0]}},{"type":"Feature","geometry":{"type":"Point","coordinates":[6.394996960923636,53.25721815663992]},"properties":{"location_id":59716,"base_color":"#B20A2F","provider_slug":"prorail","bands":["900"],"deleted":false,"is_kpn_huawei":null,"angles":[145.0,245.0]}},{"type":"Feature","geometry":{"type":"Point","coordinates":[6.145553146872594,53.26027482162225]},"properties":{"location_id":59717,"base_color":"#B20A2F","provider_slug":"prorail","bands":["900"],"deleted":false,"is_kpn_huawei":null,"angles":[255.0,95.0]}},{"type":"Feature","geometry":{"type":"Point","coordinates":[6.303888131960712,53.26638609782788]},"properties":{"location_id":59718,"base_color":"#B20A2F","provider_slug":"prorail","bands":["900"],"deleted":false,"is_kpn_huawei":null,"angles":[105.0,260.0]}},{"type":"Feature","geometry":{"type":"Point","coordinates":[6.527771728195561,53.31471872259739]},"properties":{"location_id":59719,"base_color":"#B20A2F","provider_slug":"prorail","bands":["900"],"deleted":false,"is_kpn_huawei":null,"angles":[160.0,345.0]}},{"type":"Feature","geometry":{"type":"Point","coordinates":[6.951943981045609,53.31555211695984]},"properties":{"location_id":59720,"base_color":"#B20A2F","provider_slug":"prorail","bands":["900"],"deleted":false,"is_kpn_huawei":null,"angles":[90.0,310.0]}},{"type":"Feature","geometry":{"type":"Point","coordinates":[6.8574927943322805,53.32305331061303]},"properties":{"location_id":59721,"base_color":"#B20A2F","provider_slug":"prorail","bands":["900"],"deleted":false,"is_kpn_huawei":null,"angles":[275.0,85.0]}},{"type":"Feature","geometry":{"type":"Point","coordinates":[6.689449117317904,53.32639323363907]},"properties":{"location_id":59722,"base_color":"#B20A2F","provider_slug":"prorail","bands":["900"],"deleted":false,"is_kpn_huawei":null,"angles":[80.0,245.0]}},{"type":"Feature","geometry":{"type":"Point","coordinates":[6.634728371709218,53.40222276211755]},"properties":{"location_id":59723,"base_color":"#B20A2F","provider_slug":"prorail","bands":["900"],"deleted":false,"is_kpn_huawei":null,"angles":[75.0,245.0]}},{"type":"Feature","geometry":{"type":"Point","coordinates":[6.760272717111921,53.41889111145911]},"properties":{"location_id":59724,"base_color":"#B20A2F","provider_slug":"prorail","bands":["900"],"deleted":false,"is_kpn_huawei":null,"angles":[40.0,235.0]}},{"type":"Feature","geometry":{"type":"Point","coordinates":[5.709717170817799,50.76805715964345]},"properties":{"location_id":59725,"base_color":"#B20A2F","provider_slug":"prorail","bands":["900"],"deleted":false,"is_kpn_huawei":null,"angles":[5.0,190.0]}},{"type":"Feature","geometry":{"type":"Point","coordinates":[5.716383332694094,50.838609583452566]},"properties":{"location_id":59726,"base_color":"#B20A2F","provider_slug":"prorail","bands":["900"],"deleted":false,"is_kpn_huawei":null,"angles":[330.0,175.0]}},{"type":"Feature","geometry":{"type":"Point","coordinates":[5.873334568025459,50.85639331831142]},"properties":{"location_id":59727,"base_color":"#B20A2F","provider_slug":"prorail","bands":["900"],"deleted":false,"is_kpn_huawei":null,"angles":[280.0,45.0]}},{"type":"Feature","geometry":{"type":"Point","coordinates":[6.059997739677893,50.86416808496153]},"properties":{"location_id":33331,"base_color":"#B20A2F","provider_slug":"prorail","bands":["900"],"deleted":false,"is_kpn_huawei":null,"angles":[200.0,350.0]}},{"type":"Feature","geometry":{"type":"Point","coordinates":[5.8355521652159466,50.86888777233808]},"properties":{"location_id":59728,"base_color":"#B20A2F","provider_slug":"prorail","bands":["900"],"deleted":false,"is_kpn_huawei":null,"angles":[140.0,300.0]}},{"type":"Feature","geometry":{"type":"Point","coordinates":[5.709166780771925,50.87055825068607]},"properties":{"location_id":59729,"base_color":"#B20A2F","provider_slug":"prorail","bands":["900"],"deleted":false,"is_kpn_huawei":null,"angles":[40.0,260.0,190.0]}},{"type":"Feature","geometry":{"type":"Point","coordinates":[5.763049023483651,50.88111036309622]},"properties":{"location_id":59730,"base_color":"#B20A2F","provider_slug":"prorail","bands":["900"],"deleted":false,"is_kpn_huawei":null,"angles":[265.0,110.0]}},{"type":"Feature","geometry":{"type":"Point","coordinates":[6.002779188942998,50.895831501418925]},"properties":{"location_id":59731,"base_color":"#B20A2F","provider_slug":"prorail","bands":["900"],"deleted":false,"is_kpn_huawei":null,"angles":[236.0,86.0]}},{"type":"Feature","geometry":{"type":"Point","coordinates":[6.065006438917963,50.895834203333905]},"properties":{"location_id":59732,"base_color":"#B20A2F","provider_slug":"prorail","bands":["900"],"deleted":false,"is_kpn_huawei":null,"angles":[145.0,275.0]}},{"type":"Feature","geometry":{"type":"Point","coordinates":[5.883055080138137,50.92333747929278]},"properties":{"location_id":59733,"base_color":"#B20A2F","provider_slug":"prorail","bands":["900"],"deleted":false,"is_kpn_huawei":null,"angles":[10.0,115.0]}},{"type":"Feature","geometry":{"type":"Point","coordinates":[5.7427728017491635,50.92361087627126]},"properties":{"location_id":59734,"base_color":"#B20A2F","provider_slug":"prorail","bands":["900"],"deleted":false,"is_kpn_huawei":null,"angles":[25.0,185.0]}},{"type":"Feature","geometry":{"type":"Point","coordinates":[5.769438638405003,50.94250136717345]},"properties":{"location_id":59735,"base_color":"#B20A2F","provider_slug":"prorail","bands":["900"],"deleted":false,"is_kpn_huawei":null,"angles":[254.0,55.0]}},{"type":"Feature","geometry":{"type":"Point","coordinates":[5.85333105520226,50.94305685757196]},"properties":{"location_id":59736,"base_color":"#B20A2F","provider_slug":"prorail","bands":["900"],"deleted":false,"is_kpn_huawei":null,"angles":[105.0,315.0]}},{"type":"Feature","geometry":{"type":"Point","coordinates":[5.826666169115122,50.97277958953461]},"properties":{"location_id":33342,"base_color":"#B20A2F","provider_slug":"prorail","bands":["900"],"deleted":false,"is_kpn_huawei":null,"angles":[32.0,153.0,226.0]}},{"type":"Feature","geometry":{"type":"Point","coordinates":[5.808051434749295,51.039168808602206]},"properties":{"location_id":59737,"base_color":"#B20A2F","provider_slug":"prorail","bands":["900"],"deleted":false,"is_kpn_huawei":null,"angles":[10.0,140.0]}},{"type":"Feature","geometry":{"type":"Point","coordinates":[5.860003221509609,51.04166522280801]},"properties":{"location_id":59738,"base_color":"#B20A2F","provider_slug":"prorail","bands":["900"],"deleted":false,"is_kpn_huawei":null,"angles":[0.0,190.0]}},{"type":"Feature","geometry":{"type":"Point","coordinates":[5.879161582140124,51.09861127986873]},"properties":{"location_id":59739,"base_color":"#B20A2F","provider_slug":"prorail","bands":["900"],"deleted":false,"is_kpn_huawei":null,"angles":[10.0,195.0]}},{"type":"Feature","geometry":{"type":"Point","coordinates":[5.947776099482247,51.152782181772245]},"properties":{"location_id":33347,"base_color":"#B20A2F","provider_slug":"prorail","bands":["900"],"deleted":false,"is_kpn_huawei":null,"angles":[224.0,45.0]}},{"type":"Feature","geometry":{"type":"Point","coordinates":[5.983882418350675,51.19916520294546]},"properties":{"location_id":59740,"base_color":"#B20A2F","provider_slug":"prorail","bands":["900"],"deleted":false,"is_kpn_huawei":null,"angles":[160.0,35.0]}},{"type":"Feature","geometry":{"type":"Point","coordinates":[3.80194408928604,51.223610501094775]},"properties":{"location_id":59741,"base_color":"#B20A2F","provider_slug":"prorail","bands":["900"],"deleted":false,"is_kpn_huawei":null,"angles":[0.0,185.0]}},{"type":"Feature","geometry":{"type":"Point","coordinates":[6.035557926564193,51.23639052014626]},"properties":{"location_id":33351,"base_color":"#B20A2F","provider_slug":"prorail","bands":["900"],"deleted":false,"is_kpn_huawei":null,"angles":[25.0,205.0]}},{"type":"Feature","geometry":{"type":"Point","coordinates":[5.7813865892390846,51.2469414281235]},"properties":{"location_id":33352,"base_color":"#B20A2F","provider_slug":"prorail","bands":["900"],"deleted":false,"is_kpn_huawei":null,"angles":[100.0,270.0]}},{"type":"Feature","geometry":{"type":"Point","coordinates":[5.666947326854355,51.25778102317285]},"properties":{"location_id":59743,"base_color":"#B20A2F","provider_slug":"prorail","bands":["900"],"deleted":false,"is_kpn_huawei":null,"angles":[333.0,110.0,255.0]}},{"type":"Feature","geometry":{"type":"Point","coordinates":[3.847498747041397,51.27055781071685]},"properties":{"location_id":33354,"base_color":"#B20A2F","provider_slug":"prorail","bands":["900"],"deleted":false,"is_kpn_huawei":null,"angles":[120.0,20.0]}},{"type":"Feature","geometry":{"type":"Point","coordinates":[3.8344490715562776,51.30416936932853]},"properties":{"location_id":59744,"base_color":"#B20A2F","provider_slug":"prorail","bands":["900"],"deleted":false,"is_kpn_huawei":null,"angles":[325.0,175.0]}},{"type":"Feature","geometry":{"type":"Point","coordinates":[6.122504198094248,51.32472106391534]},"properties":{"location_id":33356,"base_color":"#B20A2F","provider_slug":"prorail","bands":["900"],"deleted":false,"is_kpn_huawei":null,"angles":[210.0,45.0]}},{"type":"Feature","geometry":{"type":"Point","coordinates":[5.593326962800972,51.352775306141424]},"properties":{"location_id":59745,"base_color":"#B20A2F","provider_slug":"prorail","bands":["900"],"deleted":false,"is_kpn_huawei":null,"angles":[155.0,335.0]}},{"type":"Feature","geometry":{"type":"Point","coordinates":[6.171104237311629,51.36527733357269]},"properties":{"location_id":33358,"base_color":"#B20A2F","provider_slug":"prorail","bands":["900"],"deleted":false,"is_kpn_huawei":null,"angles":[160.0,305.0]}},{"type":"Feature","geometry":{"type":"Point","coordinates":[6.142226302219352,51.38000335430304]},"properties":{"location_id":59746,"base_color":"#B20A2F","provider_slug":"prorail","bands":["900"],"deleted":false,"is_kpn_huawei":null,"angles":[304.0,354.0,125.0]}},{"type":"Feature","geometry":{"type":"Point","coordinates":[5.557227967681343,51.41944005471564]},"properties":{"location_id":59747,"base_color":"#B20A2F","provider_slug":"prorail","bands":["900"],"deleted":false,"is_kpn_huawei":null,"angles":[170.0,315.0]}},{"type":"Feature","geometry":{"type":"Point","coordinates":[4.227781971765362,51.426387403980556]},"properties":{"location_id":59748,"base_color":"#B20A2F","provider_slug":"prorail","bands":["900"],"deleted":false,"is_kpn_huawei":null,"angles":[65.0,270.0]}},{"type":"Feature","geometry":{"type":"Point","coordinates":[6.131107580899527,51.43721803967113]},"properties":{"location_id":59749,"base_color":"#B20A2F","provider_slug":"prorail","bands":["900"],"deleted":false,"is_kpn_huawei":null,"angles":[160.0,330.0]}},{"type":"Feature","geometry":{"type":"Point","coordinates":[6.051394523752703,51.439721769268424]},"properties":{"location_id":59750,"base_color":"#B20A2F","provider_slug":"prorail","bands":["900"],"deleted":false,"is_kpn_huawei":null,"angles":[140.0,270.0]}},{"type":"Feature","geometry":{"type":"Point","coordinates":[5.473054166808521,51.441662658060025]},"properties":{"location_id":59751,"base_color":"#B20A2F","provider_slug":"prorail","bands":["900"],"deleted":false,"is_kpn_huawei":null,"angles":[315.0,95.0]}},{"type":"Feature","geometry":{"type":"Point","coordinates":[4.082226364527253,51.44860939776956]},"properties":{"location_id":33366,"base_color":"#B20A2F","provider_slug":"prorail","bands":["900"],"deleted":false,"is_kpn_huawei":null,"angles":[130.0,285.0]}},{"type":"Feature","geometry":{"type":"Point","coordinates":[5.866107032212981,51.44861188202267]},"properties":{"location_id":59752,"base_color":"#B20A2F","provider_slug":"prorail","bands":["900"],"deleted":false,"is_kpn_huawei":null,"angles":[97.0,277.0]}},{"type":"Feature","geometry":{"type":"Point","coordinates":[5.566112926910046,51.45249616646487]},"properties":{"location_id":59753,"base_color":"#B20A2F","provider_slug":"prorail","bands":["900"],"deleted":false,"is_kpn_huawei":null,"angles":[65.0,255.0]}},{"type":"Feature","geometry":{"type":"Point","coordinates":[5.693889934004815,51.47305695837035]},"properties":{"location_id":59754,"base_color":"#B20A2F","provider_slug":"prorail","bands":["900"],"deleted":false,"is_kpn_huawei":null,"angles":[100.0,285.0]}},{"type":"Feature","geometry":{"type":"Point","coordinates":[3.603329920151504,51.473331800826124]},"properties":{"location_id":59755,"base_color":"#B20A2F","provider_slug":"prorail","bands":["900"],"deleted":false,"is_kpn_huawei":null,"angles":[200.0,10.0]}},{"type":"Feature","geometry":{"type":"Point","coordinates":[4.736393499434601,51.49138640289005]},"properties":{"location_id":59756,"base_color":"#B20A2F","provider_slug":"prorail","bands":["900"],"deleted":false,"is_kpn_huawei":null,"angles":[195.0,15.0]}},{"type":"Feature","geometry":{"type":"Point","coordinates":[4.309439212846926,51.49527373026196]},"properties":{"location_id":59757,"base_color":"#B20A2F","provider_slug":"prorail","bands":["900"],"deleted":false,"is_kpn_huawei":null,"angles":[40.0,270.0,200.0]}},{"type":"Feature","geometry":{"type":"Point","coordinates":[5.404164565870664,51.495553158349274]},"properties":{"location_id":59758,"base_color":"#B20A2F","provider_slug":"prorail","bands":["900"],"deleted":false,"is_kpn_huawei":null,"angles":[330.0,140.0]}},{"type":"Feature","geometry":{"type":"Point","coordinates":[3.899724967418635,51.497497266675694]},"properties":{"location_id":59759,"base_color":"#B20A2F","provider_slug":"prorail","bands":["900"],"deleted":false,"is_kpn_huawei":null,"angles":[272.0,110.0]}},{"type":"Feature","geometry":{"type":"Point","coordinates":[3.629994858614487,51.499718742933645]},"properties":{"location_id":59760,"base_color":"#B20A2F","provider_slug":"prorail","bands":["900"],"deleted":false,"is_kpn_huawei":null,"angles":[235.0,100.0]}},{"type":"Feature","geometry":{"type":"Point","coordinates":[5.3891601824694675,51.5094418412575]},"properties":{"location_id":59761,"base_color":"#B20A2F","provider_slug":"prorail","bands":["900"],"deleted":false,"is_kpn_huawei":null,"angles":[-1.0]}},{"type":"Feature","geometry":{"type":"Point","coordinates":[6.041670003961308,51.51167000735861]},"properties":{"location_id":59762,"base_color":"#B20A2F","provider_slug":"prorail","bands":["900"],"deleted":false,"is_kpn_huawei":null,"angles":[320.0,125.0]}},{"type":"Feature","geometry":{"type":"Point","coordinates":[4.461107390834259,51.523057084035464]},"properties":{"location_id":59763,"base_color":"#B20A2F","provider_slug":"prorail","bands":["900"],"deleted":false,"is_kpn_huawei":null,"angles":[250.0,20.0,190.0]}},{"type":"Feature","geometry":{"type":"Point","coordinates":[4.742772570603445,51.533058244880074]},"properties":{"location_id":59764,"base_color":"#B20A2F","provider_slug":"prorail","bands":["900"],"deleted":false,"is_kpn_huawei":null,"angles":[180.0,350.0]}},{"type":"Feature","geometry":{"type":"Point","coordinates":[5.087215183041524,51.558890170774085]},"properties":{"location_id":59765,"base_color":"#B20A2F","provider_slug":"prorail","bands":["900"],"deleted":false,"is_kpn_huawei":null,"angles":[290.0,60.0]}},{"type":"Feature","geometry":{"type":"Point","coordinates":[4.553886109547649,51.56027810223318]},"properties":{"location_id":59766,"base_color":"#B20A2F","provider_slug":"prorail","bands":["900"],"deleted":false,"is_kpn_huawei":null,"angles":[250.0,75.0]}},{"type":"Feature","geometry":{"type":"Point","coordinates":[5.006667782088797,51.57722638417921]},"properties":{"location_id":59767,"base_color":"#B20A2F","provider_slug":"prorail","bands":["900"],"deleted":false,"is_kpn_huawei":null,"angles":[140.0]}},{"type":"Feature","geometry":{"type":"Point","coordinates":[4.643891650322402,51.57777525505888]},"properties":{"location_id":59768,"base_color":"#B20A2F","provider_slug":"prorail","bands":["900"],"deleted":false,"is_kpn_huawei":null,"angles":[250.0,70.0]}},{"type":"Feature","geometry":{"type":"Point","coordinates":[4.90860841748037,51.58305942598774]},"properties":{"location_id":59769,"base_color":"#B20A2F","provider_slug":"prorail","bands":["900"],"deleted":false,"is_kpn_huawei":null,"angles":[90.0,290.0]}},{"type":"Feature","geometry":{"type":"Point","coordinates":[5.317497710205439,51.58444010072994]},"properties":{"location_id":59770,"base_color":"#B20A2F","provider_slug":"prorail","bands":["900"],"deleted":false,"is_kpn_huawei":null,"angles":[340.0,125.0,270.0]}},{"type":"Feature","geometry":{"type":"Point","coordinates":[4.541946536368054,51.585002030745315]},"properties":{"location_id":33387,"base_color":"#B20A2F","provider_slug":"prorail","bands":["900"],"deleted":false,"is_kpn_huawei":null,"angles":[35.0,245.0]}},{"type":"Feature","geometry":{"type":"Point","coordinates":[5.998051260910178,51.59110688466514]},"properties":{"location_id":59771,"base_color":"#B20A2F","provider_slug":"prorail","bands":["900"],"deleted":false,"is_kpn_huawei":null,"angles":[320.0,170.0]}},{"type":"Feature","geometry":{"type":"Point","coordinates":[4.725550679825518,51.59138954222581]},"properties":{"location_id":59772,"base_color":"#B20A2F","provider_slug":"prorail","bands":["900"],"deleted":false,"is_kpn_huawei":null,"angles":[265.0,170.0,60.0,350.0]}},{"type":"Feature","geometry":{"type":"Point","coordinates":[4.750558514886744,51.592499135941765]},"properties":{"location_id":59773,"base_color":"#B20A2F","provider_slug":"prorail","bands":["900"],"deleted":false,"is_kpn_huawei":null,"angles":[90.0]}},{"type":"Feature","geometry":{"type":"Point","coordinates":[5.153614787072244,51.60777791070074]},"properties":{"location_id":59774,"base_color":"#B20A2F","provider_slug":"prorail","bands":["900"],"deleted":false,"is_kpn_huawei":null,"angles":[65.0,215.0]}},{"type":"Feature","geometry":{"type":"Point","coordinates":[4.6991682958506935,51.63722419009202]},"properties":{"location_id":59775,"base_color":"#B20A2F","provider_slug":"prorail","bands":["900"],"deleted":false,"is_kpn_huawei":null,"angles":[155.0,340.0]}},{"type":"Feature","geometry":{"type":"Point","coordinates":[5.23416690933609,51.637779933213686]},"properties":{"location_id":59776,"base_color":"#B20A2F","provider_slug":"prorail","bands":["900"],"deleted":false,"is_kpn_huawei":null,"angles":[65.0,220.0]}},{"type":"Feature","geometry":{"type":"Point","coordinates":[5.93721598628485,51.64388517703966]},"properties":{"location_id":59777,"base_color":"#B20A2F","provider_slug":"prorail","bands":["900"],"deleted":false,"is_kpn_huawei":null,"angles":[330.0,140.0]}},{"type":"Feature","geometry":{"type":"Point","coordinates":[5.296660719788946,51.66527788727166]},"properties":{"location_id":59778,"base_color":"#B20A2F","provider_slug":"prorail","bands":["900"],"deleted":false,"is_kpn_huawei":null,"angles":[350.0,230.0,175.0]}},{"type":"Feature","geometry":{"type":"Point","coordinates":[4.6694391142176235,51.67916726569996]},"properties":{"location_id":59779,"base_color":"#B20A2F","provider_slug":"prorail","bands":["900"],"deleted":false,"is_kpn_huawei":null,"angles":[90.0,155.0,220.0,340.0]}},{"type":"Feature","geometry":{"type":"Point","coordinates":[4.616389054694999,51.680834618199775]},"properties":{"location_id":59780,"base_color":"#B20A2F","provider_slug":"prorail","bands":["900"],"deleted":false,"is_kpn_huawei":null,"angles":[30.0,255.0]}},{"type":"Feature","geometry":{"type":"Point","coordinates":[4.8352712814190255,51.69916711852247]},"properties":{"location_id":59781,"base_color":"#B20A2F","provider_slug":"prorail","bands":["900"],"deleted":false,"is_kpn_huawei":null,"angles":[250.0,180.0]}},{"type":"Feature","geometry":{"type":"Point","coordinates":[5.352779905250659,51.71194007301235]},"properties":{"location_id":59782,"base_color":"#B20A2F","provider_slug":"prorail","bands":["900"],"deleted":false,"is_kpn_huawei":null,"angles":[250.0,60.0]}},{"type":"Feature","geometry":{"type":"Point","coordinates":[5.29556072713276,51.71610698227378]},"properties":{"location_id":33400,"base_color":"#B20A2F","provider_slug":"prorail","bands":["900"],"deleted":false,"is_kpn_huawei":null,"angles":[330.0,180.0]}},{"type":"Feature","geometry":{"type":"Point","coordinates":[4.636106365815939,51.730832651382016]},"properties":{"location_id":59783,"base_color":"#B20A2F","provider_slug":"prorail","bands":["900"],"deleted":false,"is_kpn_huawei":null,"angles":[155.0,20.0,325.0]}},{"type":"Feature","geometry":{"type":"Point","coordinates":[5.868885617853437,51.732778422488]},"properties":{"location_id":59784,"base_color":"#B20A2F","provider_slug":"prorail","bands":["900"],"deleted":false,"is_kpn_huawei":null,"angles":[0.0,155.0]}},{"type":"Feature","geometry":{"type":"Point","coordinates":[5.520280210823595,51.763058581737944]},"properties":{"location_id":59785,"base_color":"#B20A2F","provider_slug":"prorail","bands":["900"],"deleted":false,"is_kpn_huawei":null,"angles":[75.0,245.0]}},{"type":"Feature","geometry":{"type":"Point","coordinates":[4.590834829263341,51.77305982806558]},"properties":{"location_id":59786,"base_color":"#B20A2F","provider_slug":"prorail","bands":["900"],"deleted":false,"is_kpn_huawei":null,"angles":[350.0,150.0]}},{"type":"Feature","geometry":{"type":"Point","coordinates":[5.653339909285259,51.79916315490932]},"properties":{"location_id":59787,"base_color":"#B20A2F","provider_slug":"prorail","bands":["900"],"deleted":false,"is_kpn_huawei":null,"angles":[80.0,230.0]}},{"type":"Feature","geometry":{"type":"Point","coordinates":[5.268057858036949,51.80194880542476]},"properties":{"location_id":59788,"base_color":"#B20A2F","provider_slug":"prorail","bands":["900"],"deleted":false,"is_kpn_huawei":null,"angles":[345.0,180.0]}},{"type":"Feature","geometry":{"type":"Point","coordinates":[4.689723912485937,51.80305565592899]},"properties":{"location_id":33407,"base_color":"#B20A2F","provider_slug":"prorail","bands":["900"],"deleted":false,"is_kpn_huawei":null,"angles":[240.0,90.0,300.0]}},{"type":"Feature","geometry":{"type":"Point","coordinates":[4.744721486676069,51.81500095741753]},"properties":{"location_id":33408,"base_color":"#B20A2F","provider_slug":"prorail","bands":["900"],"deleted":false,"is_kpn_huawei":null,"angles":[220.0,20.0,270.0]}},{"type":"Feature","geometry":{"type":"Point","coordinates":[4.585282777185568,51.818055727566836]},"properties":{"location_id":59789,"base_color":"#B20A2F","provider_slug":"prorail","bands":["900"],"deleted":false,"is_kpn_huawei":null,"angles":[170.0,350.0]}},{"type":"Feature","geometry":{"type":"Point","coordinates":[5.866389090587455,51.819447227062184]},"properties":{"location_id":59790,"base_color":"#B20A2F","provider_slug":"prorail","bands":["900"],"deleted":false,"is_kpn_huawei":null,"angles":[170.0]}},{"type":"Feature","geometry":{"type":"Point","coordinates":[5.794717507816512,51.82333148724856]},"properties":{"location_id":59791,"base_color":"#B20A2F","provider_slug":"prorail","bands":["900"],"deleted":false,"is_kpn_huawei":null,"angles":[75.0,255.0]}},{"type":"Feature","geometry":{"type":"Point","coordinates":[4.606666895814518,51.826945923663544]},"properties":{"location_id":59792,"base_color":"#B20A2F","provider_slug":"prorail","bands":["900"],"deleted":false,"is_kpn_huawei":null,"angles":[145.0,310.0]}},{"type":"Feature","geometry":{"type":"Point","coordinates":[4.637496000301309,51.83027494730326]},"properties":{"location_id":59793,"base_color":"#B20A2F","provider_slug":"prorail","bands":["900"],"deleted":false,"is_kpn_huawei":null,"angles":[-1.0]}},{"type":"Feature","geometry":{"type":"Point","coordinates":[4.803610669761493,51.831110456060316]},"properties":{"location_id":59794,"base_color":"#B20A2F","provider_slug":"prorail","bands":["900"],"deleted":false,"is_kpn_huawei":null,"angles":[80.0,265.0]}},{"type":"Feature","geometry":{"type":"Point","coordinates":[4.73194568293744,51.833887308617406]},"properties":{"location_id":59795,"base_color":"#B20A2F","provider_slug":"prorail","bands":["900"],"deleted":false,"is_kpn_huawei":null,"angles":[291.0,102.0]}},{"type":"Feature","geometry":{"type":"Point","coordinates":[4.955835998047302,51.834447035888005]},"properties":{"location_id":59796,"base_color":"#B20A2F","provider_slug":"prorail","bands":["900"],"deleted":false,"is_kpn_huawei":null,"angles":[70.0,270.0]}},{"type":"Feature","geometry":{"type":"Point","coordinates":[4.863893102483431,51.83583497596273]},"properties":{"location_id":59797,"base_color":"#B20A2F","provider_slug":"prorail","bands":["900"],"deleted":false,"is_kpn_huawei":null,"angles":[100.0,-1.0]}},{"type":"Feature","geometry":{"type":"Point","coordinates":[4.928050326491511,51.83888982768152]},"properties":{"location_id":33418,"base_color":"#B20A2F","provider_slug":"prorail","bands":["900"],"deleted":false,"is_kpn_huawei":null,"angles":[260.0,70.0]}},{"type":"Feature","geometry":{"type":"Point","coordinates":[5.04499888294383,51.8391630457179]},"properties":{"location_id":59798,"base_color":"#B20A2F","provider_slug":"prorail","bands":["900"],"deleted":false,"is_kpn_huawei":null,"angles":[275.0,94.0]}},{"type":"Feature","geometry":{"type":"Point","coordinates":[5.852773361795253,51.842224938254255]},"properties":{"location_id":59799,"base_color":"#B20A2F","provider_slug":"prorail","bands":["900"],"deleted":false,"is_kpn_huawei":null,"angles":[145.0,10.0,230.0]}},{"type":"Feature","geometry":{"type":"Point","coordinates":[5.147216737228969,51.848332866911534]},"properties":{"location_id":59800,"base_color":"#B20A2F","provider_slug":"prorail","bands":["900"],"deleted":false,"is_kpn_huawei":null,"angles":[265.0,90.0]}},{"type":"Feature","geometry":{"type":"Point","coordinates":[6.155554423330016,51.848336351211955]},"properties":{"location_id":59801,"base_color":"#B20A2F","provider_slug":"prorail","bands":["900"],"deleted":false,"is_kpn_huawei":null,"angles":[0.0]}},{"type":"Feature","geometry":{"type":"Point","coordinates":[4.553339373291403,51.85444431213208]},"properties":{"location_id":59802,"base_color":"#B20A2F","provider_slug":"prorail","bands":["900"],"deleted":false,"is_kpn_huawei":null,"angles":[0.0,150.0]}},{"type":"Feature","geometry":{"type":"Point","coordinates":[5.22416868946375,51.85916996500294]},"properties":{"location_id":59803,"base_color":"#B20A2F","provider_slug":"prorail","bands":["900"],"deleted":false,"is_kpn_huawei":null,"angles":[240.0,90.0]}},{"type":"Feature","geometry":{"type":"Point","coordinates":[4.283048999583258,51.86833100396815]},"properties":{"location_id":59804,"base_color":"#B20A2F","provider_slug":"prorail","bands":["900"],"deleted":false,"is_kpn_huawei":null,"angles":[85.0,310.0]}},{"type":"Feature","geometry":{"type":"Point","coordinates":[4.45305315154402,51.8683321112551]},"properties":{"location_id":59805,"base_color":"#B20A2F","provider_slug":"prorail","bands":["900"],"deleted":false,"is_kpn_huawei":null,"angles":[10.0,300.0,90.0]}},{"type":"Feature","geometry":{"type":"Point","coordinates":[5.326104348557515,51.86888461392189]},"properties":{"location_id":33428,"base_color":"#B20A2F","provider_slug":"prorail","bands":["900"],"deleted":false,"is_kpn_huawei":null,"angles":[243.0,53.0]}},{"type":"Feature","geometry":{"type":"Point","coordinates":[4.318061770209827,51.87000331575864]},"properties":{"location_id":33429,"base_color":"#B20A2F","provider_slug":"prorail","bands":["900"],"deleted":false,"is_kpn_huawei":null,"angles":[-1.0]}},{"type":"Feature","geometry":{"type":"Point","coordinates":[4.989448011578985,51.871112631209506]},"properties":{"location_id":33430,"base_color":"#B20A2F","provider_slug":"prorail","bands":["900"],"deleted":false,"is_kpn_huawei":null,"angles":[65.0,195.0]}},{"type":"Feature","geometry":{"type":"Point","coordinates":[4.525281638121861,51.87638999691075]},"properties":{"location_id":59806,"base_color":"#B20A2F","provider_slug":"prorail","bands":["900"],"deleted":false,"is_kpn_huawei":null,"angles":[345.0,130.0,255.0]}},{"type":"Feature","geometry":{"type":"Point","coordinates":[5.269447592708076,51.88610808937662]},"properties":{"location_id":59807,"base_color":"#B20A2F","provider_slug":"prorail","bands":["900"],"deleted":false,"is_kpn_huawei":null,"angles":[320.0,180.0,100.0]}},{"type":"Feature","geometry":{"type":"Point","coordinates":[4.374437849496452,51.89361346659041]},"properties":{"location_id":59808,"base_color":"#B20A2F","provider_slug":"prorail","bands":["900"],"deleted":false,"is_kpn_huawei":null,"angles":[160.0,240.0,100.0]}},{"type":"Feature","geometry":{"type":"Point","coordinates":[5.805832552439249,51.89555927647177]},"properties":{"location_id":59809,"base_color":"#B20A2F","provider_slug":"prorail","bands":["900"],"deleted":false,"is_kpn_huawei":null,"angles":[305.0,90.0]}},{"type":"Feature","geometry":{"type":"Point","coordinates":[5.4172179543934,51.895834465656876]},"properties":{"location_id":33438,"base_color":"#B20A2F","provider_slug":"prorail","bands":["900"],"deleted":false,"is_kpn_huawei":null,"angles":[60.0,230.0]}},{"type":"Feature","geometry":{"type":"Point","coordinates":[4.416384760851054,51.89750017731764]},"properties":{"location_id":59810,"base_color":"#B20A2F","provider_slug":"prorail","bands":["900"],"deleted":false,"is_kpn_huawei":null,"angles":[200.0,125.0]}},{"type":"Feature","geometry":{"type":"Point","coordinates":[4.34527156329358,51.90083720644262]},"properties":{"location_id":59811,"base_color":"#B20A2F","provider_slug":"prorail","bands":["900"],"deleted":false,"is_kpn_huawei":null,"angles":[50.0]}},{"type":"Feature","geometry":{"type":"Point","coordinates":[5.103606784146088,51.90111414452478]},"properties":{"location_id":59812,"base_color":"#B20A2F","provider_slug":"prorail","bands":["900"],"deleted":false,"is_kpn_huawei":null,"angles":[240.0,110.0]}},{"type":"Feature","geometry":{"type":"Point","coordinates":[4.22805772468763,51.90166297901516]},"properties":{"location_id":59813,"base_color":"#B20A2F","provider_slug":"prorail","bands":["900"],"deleted":false,"is_kpn_huawei":null,"angles":[300.0]}},{"type":"Feature","geometry":{"type":"Point","coordinates":[6.137217427487694,51.901946334046265]},"properties":{"location_id":59814,"base_color":"#B20A2F","provider_slug":"prorail","bands":["900"],"deleted":false,"is_kpn_huawei":null,"angles":[305.0,150.0]}},{"type":"Feature","geometry":{"type":"Point","coordinates":[5.904450119247873,51.903058171410535]},"properties":{"location_id":59815,"base_color":"#B20A2F","provider_slug":"prorail","bands":["900"],"deleted":false,"is_kpn_huawei":null,"angles":[90.0,260.0]}},{"type":"Feature","geometry":{"type":"Point","coordinates":[4.507222372884564,51.90722230390425]},"properties":{"location_id":59816,"base_color":"#B20A2F","provider_slug":"prorail","bands":["900"],"deleted":false,"is_kpn_huawei":null,"angles":[-1.0]}},{"type":"Feature","geometry":{"type":"Point","coordinates":[5.862224291692764,51.90999581328296]},"properties":{"location_id":59817,"base_color":"#B20A2F","provider_slug":"prorail","bands":["900"],"deleted":false,"is_kpn_huawei":null,"angles":[345.0,275.0,180.0]}},{"type":"Feature","geometry":{"type":"Point","coordinates":[5.181395692982402,51.911666513507356]},"properties":{"location_id":59818,"base_color":"#B20A2F","provider_slug":"prorail","bands":["900"],"deleted":false,"is_kpn_huawei":null,"angles":[115.0,215.0]}},{"type":"Feature","geometry":{"type":"Point","coordinates":[5.530833645180317,51.9155515201478]},"properties":{"location_id":59819,"base_color":"#B20A2F","provider_slug":"prorail","bands":["900"],"deleted":false,"is_kpn_huawei":null,"angles":[90.0,245.0]}},{"type":"Feature","geometry":{"type":"Point","coordinates":[5.723613140668232,51.91833038703944]},"properties":{"location_id":59820,"base_color":"#B20A2F","provider_slug":"prorail","bands":["900"],"deleted":false,"is_kpn_huawei":null,"angles":[100.0,270.0]}},{"type":"Feature","geometry":{"type":"Point","coordinates":[4.431944808605419,51.91944353666491]},"properties":{"location_id":59821,"base_color":"#B20A2F","provider_slug":"prorail","bands":["900"],"deleted":false,"is_kpn_huawei":null,"angles":[60.0,270.0]}},{"type":"Feature","geometry":{"type":"Point","coordinates":[6.076117197544456,51.921942562421826]},"properties":{"location_id":59822,"base_color":"#B20A2F","provider_slug":"prorail","bands":["900"],"deleted":false,"is_kpn_huawei":null,"angles":[290.0,95.0]}},{"type":"Feature","geometry":{"type":"Point","coordinates":[6.359441436278157,51.9222229428413]},"properties":{"location_id":59823,"base_color":"#B20A2F","provider_slug":"prorail","bands":["900"],"deleted":false,"is_kpn_huawei":null,"angles":[90.0,315.0]}},{"type":"Feature","geometry":{"type":"Point","coordinates":[5.573326237079891,51.92444416129773]},"properties":{"location_id":33454,"base_color":"#B20A2F","provider_slug":"prorail","bands":["900"],"deleted":false,"is_kpn_huawei":null,"angles":[250.0,85.0,5.0]}},{"type":"Feature","geometry":{"type":"Point","coordinates":[5.9988867329334274,51.92444634077931]},"properties":{"location_id":59825,"base_color":"#B20A2F","provider_slug":"prorail","bands":["900"],"deleted":false,"is_kpn_huawei":null,"angles":[245.0,85.0]}},{"type":"Feature","geometry":{"type":"Point","coordinates":[4.480839242370234,51.925556564103715]},"properties":{"location_id":59826,"base_color":"#B20A2F","provider_slug":"prorail","bands":["900"],"deleted":false,"is_kpn_huawei":null,"angles":[-1.0]}},{"type":"Feature","geometry":{"type":"Point","coordinates":[6.59945047834242,51.92555615168663]},"properties":{"location_id":59827,"base_color":"#B20A2F","provider_slug":"prorail","bands":["900"],"deleted":false,"is_kpn_huawei":null,"angles":[260.0,70.0]}},{"type":"Feature","geometry":{"type":"Point","coordinates":[4.472506160323723,51.92639089064978]},"properties":{"location_id":59828,"base_color":"#B20A2F","provider_slug":"prorail","bands":["900"],"deleted":false,"is_kpn_huawei":null,"angles":[230.0]}},{"type":"Feature","geometry":{"type":"Point","coordinates":[5.665829484388991,51.92694864151215]},"properties":{"location_id":59829,"base_color":"#B20A2F","provider_slug":"prorail","bands":["900"],"deleted":false,"is_kpn_huawei":null,"angles":[110.0,255.0]}},{"type":"Feature","geometry":{"type":"Point","coordinates":[4.0386125213079085,51.92722050749021]},"properties":{"location_id":59830,"base_color":"#B20A2F","provider_slug":"prorail","bands":["900"],"deleted":false,"is_kpn_huawei":null,"angles":[75.0,340.0]}},{"type":"Feature","geometry":{"type":"Point","coordinates":[4.183892075683514,51.93277973028572]},"properties":{"location_id":59831,"base_color":"#B20A2F","provider_slug":"prorail","bands":["900"],"deleted":false,"is_kpn_huawei":null,"angles":[180.0]}},{"type":"Feature","geometry":{"type":"Point","coordinates":[6.136388051803754,51.93500264978621]},"properties":{"location_id":59832,"base_color":"#B20A2F","provider_slug":"prorail","bands":["900"],"deleted":false,"is_kpn_huawei":null,"angles":[65.0,245.0]}},{"type":"Feature","geometry":{"type":"Point","coordinates":[4.143333923190274,51.93861400844147]},"properties":{"location_id":59833,"base_color":"#B20A2F","provider_slug":"prorail","bands":["900"],"deleted":false,"is_kpn_huawei":null,"angles":[115.0,270.0]}},{"type":"Feature","geometry":{"type":"Point","coordinates":[4.46250007382658,51.94138671942895]},"properties":{"location_id":59834,"base_color":"#B20A2F","provider_slug":"prorail","bands":["900"],"deleted":false,"is_kpn_huawei":null,"angles":[80.0,200.0]}},{"type":"Feature","geometry":{"type":"Point","coordinates":[6.455838654829637,51.94472099272513]},"properties":{"location_id":59835,"base_color":"#B20A2F","provider_slug":"prorail","bands":["900"],"deleted":false,"is_kpn_huawei":null,"angles":[115.0,235.0]}},{"type":"Feature","geometry":{"type":"Point","coordinates":[5.999172432704461,51.94861479912658]},"properties":{"location_id":59836,"base_color":"#B20A2F","provider_slug":"prorail","bands":["900"],"deleted":false,"is_kpn_huawei":null,"angles":[120.0,300.0]}},{"type":"Feature","geometry":{"type":"Point","coordinates":[4.550549455393824,51.95222133704009]},"properties":{"location_id":59837,"base_color":"#B20A2F","provider_slug":"prorail","bands":["900"],"deleted":false,"is_kpn_huawei":null,"angles":[85.0,255.0]}},{"type":"Feature","geometry":{"type":"Point","coordinates":[5.852226517863858,51.95361140463591]},"properties":{"location_id":59838,"base_color":"#B20A2F","provider_slug":"prorail","bands":["900"],"deleted":false,"is_kpn_huawei":null,"angles":[0.0,180.0]}},{"type":"Feature","geometry":{"type":"Point","coordinates":[4.121109072732117,51.95417072069093]},"properties":{"location_id":59839,"base_color":"#B20A2F","provider_slug":"prorail","bands":["900"],"deleted":false,"is_kpn_huawei":null,"angles":[190.0]}},{"type":"Feature","geometry":{"type":"Point","coordinates":[6.311111961630518,51.955835245186925]},"properties":{"location_id":59840,"base_color":"#B20A2F","provider_slug":"prorail","bands":["900"],"deleted":false,"is_kpn_huawei":null,"angles":[280.0,145.0]}},{"type":"Feature","geometry":{"type":"Point","coordinates":[4.577493277247713,51.95611323648751]},"properties":{"location_id":59841,"base_color":"#B20A2F","provider_slug":"prorail","bands":["900"],"deleted":false,"is_kpn_huawei":null,"angles":[-1.0]}},{"type":"Feature","geometry":{"type":"Point","coordinates":[6.213052288334985,51.95722115018388]},"properties":{"location_id":59842,"base_color":"#B20A2F","provider_slug":"prorail","bands":["900"],"deleted":false,"is_kpn_huawei":null,"angles":[240.0,85.0]}},{"type":"Feature","geometry":{"type":"Point","coordinates":[4.6150006979316,51.9627743189078]},"properties":{"location_id":59843,"base_color":"#B20A2F","provider_slug":"prorail","bands":["900"],"deleted":false,"is_kpn_huawei":null,"angles":[240.0,30.0]}},{"type":"Feature","geometry":{"type":"Point","coordinates":[6.71944086520289,51.96416936967131]},"properties":{"location_id":59844,"base_color":"#B20A2F","provider_slug":"prorail","bands":["900"],"deleted":false,"is_kpn_huawei":null,"angles":[310.0,215.0]}},{"type":"Feature","geometry":{"type":"Point","coordinates":[5.206673216460339,51.968612604954764]},"properties":{"location_id":59845,"base_color":"#B20A2F","provider_slug":"prorail","bands":["900"],"deleted":false,"is_kpn_huawei":null,"angles":[340.0,150.0]}},{"type":"Feature","geometry":{"type":"Point","coordinates":[4.4652791224174235,51.972500480273865]},"properties":{"location_id":59846,"base_color":"#B20A2F","provider_slug":"prorail","bands":["900"],"deleted":false,"is_kpn_huawei":null,"angles":[190.0,30.0]}},{"type":"Feature","geometry":{"type":"Point","coordinates":[4.047228197653276,51.97667015299326]},"properties":{"location_id":59847,"base_color":"#B20A2F","provider_slug":"prorail","bands":["900"],"deleted":false,"is_kpn_huawei":null,"angles":[300.0,230.0]}},{"type":"Feature","geometry":{"type":"Point","coordinates":[5.9038893368948955,51.984441419074145]},"properties":{"location_id":59848,"base_color":"#B20A2F","provider_slug":"prorail","bands":["900"],"deleted":false,"is_kpn_huawei":null,"angles":[280.0,75.0]}},{"type":"Feature","geometry":{"type":"Point","coordinates":[5.953885865103394,51.985002113655035]},"properties":{"location_id":59849,"base_color":"#B20A2F","provider_slug":"prorail","bands":["900"],"deleted":false,"is_kpn_huawei":null,"angles":[160.0,60.0,270.0]}},{"type":"Feature","geometry":{"type":"Point","coordinates":[5.8758297568019495,51.98638597703896]},"properties":{"location_id":59850,"base_color":"#B20A2F","provider_slug":"prorail","bands":["900"],"deleted":false,"is_kpn_huawei":null,"angles":[90.0,235.0,285.0]}},{"type":"Feature","geometry":{"type":"Point","coordinates":[4.360004421516133,51.990558713943855]},"properties":{"location_id":59851,"base_color":"#B20A2F","provider_slug":"prorail","bands":["900"],"deleted":false,"is_kpn_huawei":null,"angles":[160.0]}},{"type":"Feature","geometry":{"type":"Point","coordinates":[5.830839822400412,51.99750302888459]},"properties":{"location_id":59852,"base_color":"#B20A2F","provider_slug":"prorail","bands":["900"],"deleted":false,"is_kpn_huawei":null,"angles":[120.0,290.0]}},{"type":"Feature","geometry":{"type":"Point","coordinates":[4.360839327498202,51.99861095747791]},"properties":{"location_id":59853,"base_color":"#B20A2F","provider_slug":"prorail","bands":["900"],"deleted":false,"is_kpn_huawei":null,"angles":[160.0,335.0]}},{"type":"Feature","geometry":{"type":"Point","coordinates":[4.652226795533709,51.99972181933188]},"properties":{"location_id":59854,"base_color":"#B20A2F","provider_slug":"prorail","bands":["900"],"deleted":false,"is_kpn_huawei":null,"angles":[40.0,210.0,330.0]}},{"type":"Feature","geometry":{"type":"Point","coordinates":[4.501111144055928,52.00416413124911]},"properties":{"location_id":59855,"base_color":"#B20A2F","provider_slug":"prorail","bands":["900"],"deleted":false,"is_kpn_huawei":null,"angles":[30.0,215.0]}},{"type":"Feature","geometry":{"type":"Point","coordinates":[6.5941617737833145,52.01277742461408]},"properties":{"location_id":59856,"base_color":"#B20A2F","provider_slug":"prorail","bands":["900"],"deleted":false,"is_kpn_huawei":null,"angles":[120.0,295.0]}},{"type":"Feature","geometry":{"type":"Point","coordinates":[4.73638892709345,52.01333135464144]},"properties":{"location_id":59857,"base_color":"#B20A2F","provider_slug":"prorail","bands":["900"],"deleted":false,"is_kpn_huawei":null,"angles":[280.0,75.0]}},{"type":"Feature","geometry":{"type":"Point","coordinates":[6.056951647530565,52.01805903748316]},"properties":{"location_id":59858,"base_color":"#B20A2F","provider_slug":"prorail","bands":["900"],"deleted":false,"is_kpn_huawei":null,"angles":[235.0,45.0]}},{"type":"Feature","geometry":{"type":"Point","coordinates":[5.715835353179066,52.01944328114232]},"properties":{"location_id":59859,"base_color":"#B20A2F","provider_slug":"prorail","bands":["900"],"deleted":false,"is_kpn_huawei":null,"angles":[105.0,285.0]}},{"type":"Feature","geometry":{"type":"Point","coordinates":[5.553050480185528,52.02389300739502]},"properties":{"location_id":59860,"base_color":"#B20A2F","provider_slug":"prorail","bands":["900"],"deleted":false,"is_kpn_huawei":null,"angles":[290.0,180.0]}},{"type":"Feature","geometry":{"type":"Point","coordinates":[4.551117314411665,52.02639011888937]},"properties":{"location_id":59861,"base_color":"#B20A2F","provider_slug":"prorail","bands":["900"],"deleted":false,"is_kpn_huawei":null,"angles":[100.0,300.0]}},{"type":"Feature","geometry":{"type":"Point","coordinates":[5.1713942288264025,52.03027502228782]},"properties":{"location_id":59862,"base_color":"#B20A2F","provider_slug":"prorail","bands":["900"],"deleted":false,"is_kpn_huawei":null,"angles":[160.0,335.0]}},{"type":"Feature","geometry":{"type":"Point","coordinates":[5.634450316997417,52.03416732927746]},"properties":{"location_id":59863,"base_color":"#B20A2F","provider_slug":"prorail","bands":["900"],"deleted":false,"is_kpn_huawei":null,"angles":[105.0,285.0]}},{"type":"Feature","geometry":{"type":"Point","coordinates":[4.322219501609525,52.037225236375726]},"properties":{"location_id":59864,"base_color":"#B20A2F","provider_slug":"prorail","bands":["900"],"deleted":false,"is_kpn_huawei":null,"angles":[-1.0]}},{"type":"Feature","geometry":{"type":"Point","coordinates":[4.527493466777161,52.03722196851687]},"properties":{"location_id":59865,"base_color":"#B20A2F","provider_slug":"prorail","bands":["900"],"deleted":false,"is_kpn_huawei":null,"angles":[110.0,290.0,205.0,30.0]}},{"type":"Feature","geometry":{"type":"Point","coordinates":[5.6741700672853055,52.04222042156277]},"properties":{"location_id":59866,"base_color":"#B20A2F","provider_slug":"prorail","bands":["900"],"deleted":false,"is_kpn_huawei":null,"angles":[320.0,230.0]}},{"type":"Feature","geometry":{"type":"Point","coordinates":[4.476667117719794,52.04888462971817]},"properties":{"location_id":59867,"base_color":"#B20A2F","provider_slug":"prorail","bands":["900"],"deleted":false,"is_kpn_huawei":null,"angles":[275.0,100.0]}},{"type":"Feature","geometry":{"type":"Point","coordinates":[6.102498125998018,52.04944816218725]},"properties":{"location_id":59868,"base_color":"#B20A2F","provider_slug":"prorail","bands":["900"],"deleted":false,"is_kpn_huawei":null,"angles":[210.0,45.0]}},{"type":"Feature","geometry":{"type":"Point","coordinates":[5.464442476415701,52.05222523260702]},"properties":{"location_id":59869,"base_color":"#B20A2F","provider_slug":"prorail","bands":["900"],"deleted":false,"is_kpn_huawei":null,"angles":[130.0,270.0,95.0]}},{"type":"Feature","geometry":{"type":"Point","coordinates":[4.308050376789947,52.05666479726189]},"properties":{"location_id":59870,"base_color":"#B20A2F","provider_slug":"prorail","bands":["900"],"deleted":false,"is_kpn_huawei":null,"angles":[20.0,165.0]}},{"type":"Feature","geometry":{"type":"Point","coordinates":[5.178332470177494,52.061107764988776]},"properties":{"location_id":59871,"base_color":"#B20A2F","provider_slug":"prorail","bands":["900"],"deleted":false,"is_kpn_huawei":null,"angles":[80.0,290.0]}},{"type":"Feature","geometry":{"type":"Point","coordinates":[5.323606568753742,52.064718018271435]},"properties":{"location_id":59872,"base_color":"#B20A2F","provider_slug":"prorail","bands":["900"],"deleted":false,"is_kpn_huawei":null,"angles":[90.0,270.0]}},{"type":"Feature","geometry":{"type":"Point","coordinates":[5.140002832575975,52.070552003931475]},"properties":{"location_id":59873,"base_color":"#B20A2F","provider_slug":"prorail","bands":["900"],"deleted":false,"is_kpn_huawei":null,"angles":[310.0,115.0,150.0]}},{"type":"Feature","geometry":{"type":"Point","coordinates":[4.335270907532906,52.07416938028391]},"properties":{"location_id":59874,"base_color":"#B20A2F","provider_slug":"prorail","bands":["900"],"deleted":false,"is_kpn_huawei":null,"angles":[315.0,50.0,115.0,235.0]}},{"type":"Feature","geometry":{"type":"Point","coordinates":[4.627506792901112,52.077503602176535]},"properties":{"location_id":59875,"base_color":"#B20A2F","provider_slug":"prorail","bands":["900"],"deleted":false,"is_kpn_huawei":null,"angles":[35.0,155.0]}},{"type":"Feature","geometry":{"type":"Point","coordinates":[6.459437445598893,52.0788912134902]},"properties":{"location_id":59876,"base_color":"#B20A2F","provider_slug":"prorail","bands":["900"],"deleted":false,"is_kpn_huawei":null,"angles":[130.0,285.0]}},{"type":"Feature","geometry":{"type":"Point","coordinates":[4.744720105151929,52.07944134600949]},"properties":{"location_id":59877,"base_color":"#B20A2F","provider_slug":"prorail","bands":["900"],"deleted":false,"is_kpn_huawei":null,"angles":[100.0,325.0]}},{"type":"Feature","geometry":{"type":"Point","coordinates":[4.359450987058325,52.08583434723667]},"properties":{"location_id":59878,"base_color":"#B20A2F","provider_slug":"prorail","bands":["900"],"deleted":false,"is_kpn_huawei":null,"angles":[50.0,230.0]}},{"type":"Feature","geometry":{"type":"Point","coordinates":[5.6163847827774065,52.086388801672]},"properties":{"location_id":59879,"base_color":"#B20A2F","provider_slug":"prorail","bands":["900"],"deleted":false,"is_kpn_huawei":null,"angles":[0.0,150.0]}},{"type":"Feature","geometry":{"type":"Point","coordinates":[5.110276695106889,52.089720416449]},"properties":{"location_id":59880,"base_color":"#B20A2F","provider_slug":"prorail","bands":["900"],"deleted":false,"is_kpn_huawei":null,"angles":[145.0,325.0,-1.0]}},{"type":"Feature","geometry":{"type":"Point","coordinates":[4.56417147003112,52.09388661974251]},"properties":{"location_id":59881,"base_color":"#B20A2F","provider_slug":"prorail","bands":["900"],"deleted":false,"is_kpn_huawei":null,"angles":[40.0,185.0,205.0]}},{"type":"Feature","geometry":{"type":"Point","coordinates":[5.094722667945073,52.098608011325005]},"properties":{"location_id":59882,"base_color":"#B20A2F","provider_slug":"prorail","bands":["900"],"deleted":false,"is_kpn_huawei":null,"angles":[275.0,315.0,75.0]}},{"type":"Feature","geometry":{"type":"Point","coordinates":[6.325837241779606,52.10750057131211]},"properties":{"location_id":59883,"base_color":"#B20A2F","provider_slug":"prorail","bands":["900"],"deleted":false,"is_kpn_huawei":null,"angles":[125.0,295.0]}},{"type":"Feature","geometry":{"type":"Point","coordinates":[4.945838587437575,52.1083372160406]},"properties":{"location_id":59884,"base_color":"#B20A2F","provider_slug":"prorail","bands":["900"],"deleted":false,"is_kpn_huawei":null,"angles":[35.0,230.0,95.0]}},{"type":"Feature","geometry":{"type":"Point","coordinates":[5.421117010475124,52.113885681392354]},"properties":{"location_id":59886,"base_color":"#B20A2F","provider_slug":"prorail","bands":["900"],"deleted":false,"is_kpn_huawei":null,"angles":[330.0]}},{"type":"Feature","geometry":{"type":"Point","coordinates":[4.428053399057063,52.121387136139695]},"properties":{"location_id":59887,"base_color":"#B20A2F","provider_slug":"prorail","bands":["900"],"deleted":false,"is_kpn_huawei":null,"angles":[35.0,220.0]}},{"type":"Feature","geometry":{"type":"Point","coordinates":[4.646663800720142,52.1372181424516]},"properties":{"location_id":59888,"base_color":"#B20A2F","provider_slug":"prorail","bands":["900"],"deleted":false,"is_kpn_huawei":null,"angles":[185.0,130.0,260.0]}},{"type":"Feature","geometry":{"type":"Point","coordinates":[6.1747155695277165,52.13944637425384]},"properties":{"location_id":59889,"base_color":"#B20A2F","provider_slug":"prorail","bands":["900"],"deleted":false,"is_kpn_huawei":null,"angles":[315.0,60.0,205.0]}},{"type":"Feature","geometry":{"type":"Point","coordinates":[4.484162457559963,52.14777984116118]},"properties":{"location_id":59890,"base_color":"#B20A2F","provider_slug":"prorail","bands":["900"],"deleted":false,"is_kpn_huawei":null,"angles":[330.0,110.0]}},{"type":"Feature","geometry":{"type":"Point","coordinates":[5.272496951649655,52.14860942144922]},"properties":{"location_id":59891,"base_color":"#B20A2F","provider_slug":"prorail","bands":["900"],"deleted":false,"is_kpn_huawei":null,"angles":[40.0,240.0,95.0]}},{"type":"Feature","geometry":{"type":"Point","coordinates":[5.377778790588747,52.15360804112109]},"properties":{"location_id":54594,"base_color":"#B20A2F","provider_slug":"prorail","bands":["900"],"deleted":false,"is_kpn_huawei":null,"angles":[250.0,60.0,300.0]}},{"type":"Feature","geometry":{"type":"Point","coordinates":[5.365839336093384,52.15639275442972]},"properties":{"location_id":59892,"base_color":"#B20A2F","provider_slug":"prorail","bands":["900"],"deleted":false,"is_kpn_huawei":null,"angles":[0.0]}},{"type":"Feature","geometry":{"type":"Point","coordinates":[5.536950571850847,52.16305832830754]},"properties":{"location_id":59893,"base_color":"#B20A2F","provider_slug":"prorail","bands":["900"],"deleted":false,"is_kpn_huawei":null,"angles":[90.0,270.0]}},{"type":"Feature","geometry":{"type":"Point","coordinates":[4.560001330958831,52.16388584673359]},"properties":{"location_id":59894,"base_color":"#B20A2F","provider_slug":"prorail","bands":["900"],"deleted":false,"is_kpn_huawei":null,"angles":[40.0,185.0,205.0]}},{"type":"Feature","geometry":{"type":"Point","coordinates":[6.308603932859918,52.16444365488672]},"properties":{"location_id":59895,"base_color":"#B20A2F","provider_slug":"prorail","bands":["900"],"deleted":false,"is_kpn_huawei":null,"angles":[80.0,275.0]}},{"type":"Feature","geometry":{"type":"Point","coordinates":[5.61000703585512,52.16500111331622]},"properties":{"location_id":59896,"base_color":"#B20A2F","provider_slug":"prorail","bands":["900"],"deleted":false,"is_kpn_huawei":null,"angles":[65.0,260.0,205.0]}},{"type":"Feature","geometry":{"type":"Point","coordinates":[6.412227778750643,52.16666272470398]},"properties":{"location_id":33531,"base_color":"#B20A2F","provider_slug":"prorail","bands":["900"],"deleted":false,"is_kpn_huawei":null,"angles":[80.0,275.0]}},{"type":"Feature","geometry":{"type":"Point","coordinates":[5.391383987639641,52.16833053228895]},"properties":{"location_id":59897,"base_color":"#B20A2F","provider_slug":"prorail","bands":["900"],"deleted":false,"is_kpn_huawei":null,"angles":[50.0,95.0]}},{"type":"Feature","geometry":{"type":"Point","coordinates":[6.2272192292404736,52.17138811133821]},"properties":{"location_id":59898,"base_color":"#B20A2F","provider_slug":"prorail","bands":["900"],"deleted":false,"is_kpn_huawei":null,"angles":[210.0,10.0,130.0]}},{"type":"Feature","geometry":{"type":"Point","coordinates":[4.4952759972658765,52.175836267849796]},"properties":{"location_id":59899,"base_color":"#B20A2F","provider_slug":"prorail","bands":["900"],"deleted":false,"is_kpn_huawei":null,"angles":[220.0,350.0]}},{"type":"Feature","geometry":{"type":"Point","coordinates":[4.98999671303217,52.17722577012389]},"properties":{"location_id":59900,"base_color":"#B20A2F","provider_slug":"prorail","bands":["900"],"deleted":false,"is_kpn_huawei":null,"angles":[160.0,20.0]}},{"type":"Feature","geometry":{"type":"Point","coordinates":[6.086666529653476,52.17722181265805]},"properties":{"location_id":33536,"base_color":"#B20A2F","provider_slug":"prorail","bands":["900"],"deleted":false,"is_kpn_huawei":null,"angles":[120.0,295.0]}},{"type":"Feature","geometry":{"type":"Point","coordinates":[5.892228201408517,52.18583630949745]},"properties":{"location_id":59901,"base_color":"#B20A2F","provider_slug":"prorail","bands":["900"],"deleted":false,"is_kpn_huawei":null,"angles":[300.0,70.0]}},{"type":"Feature","geometry":{"type":"Point","coordinates":[4.601943053731291,52.18833287152779]},"properties":{"location_id":59902,"base_color":"#B20A2F","provider_slug":"prorail","bands":["900"],"deleted":false,"is_kpn_huawei":null,"angles":[35.0,220.0]}},{"type":"Feature","geometry":{"type":"Point","coordinates":[5.6969412910232835,52.192218028493]},"properties":{"location_id":59903,"base_color":"#B20A2F","provider_slug":"prorail","bands":["900"],"deleted":false,"is_kpn_huawei":null,"angles":[240.0,85.0]}},{"type":"Feature","geometry":{"type":"Point","coordinates":[5.297502943818128,52.19583553571456]},"properties":{"location_id":59904,"base_color":"#B20A2F","provider_slug":"prorail","bands":["900"],"deleted":false,"is_kpn_huawei":null,"angles":[170.0,130.0,330.0]}},{"type":"Feature","geometry":{"type":"Point","coordinates":[5.184994764615323,52.20028039473662]},"properties":{"location_id":59905,"base_color":"#B20A2F","provider_slug":"prorail","bands":["900"],"deleted":false,"is_kpn_huawei":null,"angles":[200.0]}},{"type":"Feature","geometry":{"type":"Point","coordinates":[5.27778378216438,52.209165903720894]},"properties":{"location_id":59906,"base_color":"#B20A2F","provider_slug":"prorail","bands":["900"],"deleted":false,"is_kpn_huawei":null,"angles":[280.0,115.0]}},{"type":"Feature","geometry":{"type":"Point","coordinates":[5.9661062968835,52.20971975812299]},"properties":{"location_id":59907,"base_color":"#B20A2F","provider_slug":"prorail","bands":["900"],"deleted":false,"is_kpn_huawei":null,"angles":[240.0,90.0]}},{"type":"Feature","geometry":{"type":"Point","coordinates":[6.223339264409165,52.214721236227795]},"properties":{"location_id":59908,"base_color":"#B20A2F","provider_slug":"prorail","bands":["900"],"deleted":false,"is_kpn_huawei":null,"angles":[170.0,340.0]}},{"type":"Feature","geometry":{"type":"Point","coordinates":[5.482225335893758,52.21500220942958]},"properties":{"location_id":33546,"base_color":"#B20A2F","provider_slug":"prorail","bands":["900"],"deleted":false,"is_kpn_huawei":null,"angles":[40.0,230.0]}},{"type":"Feature","geometry":{"type":"Point","coordinates":[4.626115118202302,52.21583329959665]},"properties":{"location_id":59909,"base_color":"#B20A2F","provider_slug":"prorail","bands":["900"],"deleted":false,"is_kpn_huawei":null,"angles":[200.0,10.0]}},{"type":"Feature","geometry":{"type":"Point","coordinates":[6.858326922891036,52.22222360611147]},"properties":{"location_id":59910,"base_color":"#B20A2F","provider_slug":"prorail","bands":["900"],"deleted":false,"is_kpn_huawei":null,"angles":[320.0,90.0]}},{"type":"Feature","geometry":{"type":"Point","coordinates":[5.1824970311518594,52.22500170204109]},"properties":{"location_id":59911,"base_color":"#B20A2F","provider_slug":"prorail","bands":["900"],"deleted":false,"is_kpn_huawei":null,"angles":[120.0,165.0,350.0]}},{"type":"Feature","geometry":{"type":"Point","coordinates":[4.4827817814084705,52.22888923801326]},"properties":{"location_id":59912,"base_color":"#B20A2F","provider_slug":"prorail","bands":["900"],"deleted":false,"is_kpn_huawei":null,"angles":[25.0,170.0]}},{"type":"Feature","geometry":{"type":"Point","coordinates":[6.587502401151428,52.23166966718858]},"properties":{"location_id":59913,"base_color":"#B20A2F","provider_slug":"prorail","bands":["900"],"deleted":false,"is_kpn_huawei":null,"angles":[80.0,245.0]}},{"type":"Feature","geometry":{"type":"Point","coordinates":[6.087216916214702,52.23555156958513]},"properties":{"location_id":59914,"base_color":"#B20A2F","provider_slug":"prorail","bands":["900"],"deleted":false,"is_kpn_huawei":null,"angles":[250.0,70.0]}},{"type":"Feature","geometry":{"type":"Point","coordinates":[4.563608691926682,52.24083258925838]},"properties":{"location_id":59915,"base_color":"#B20A2F","provider_slug":"prorail","bands":["900"],"deleted":false,"is_kpn_huawei":null,"angles":[110.0,230.0]}},{"type":"Feature","geometry":{"type":"Point","coordinates":[5.0097269552414065,52.241940665148896]},"properties":{"location_id":59916,"base_color":"#B20A2F","provider_slug":"prorail","bands":["900"],"deleted":false,"is_kpn_huawei":null,"angles":[330.0,188.0]}},{"type":"Feature","geometry":{"type":"Point","coordinates":[6.185276921861457,52.24805225371678]},"properties":{"location_id":33556,"base_color":"#B20A2F","provider_slug":"prorail","bands":["900"],"deleted":false,"is_kpn_huawei":null,"angles":[120.0,350.0]}},{"type":"Feature","geometry":{"type":"Point","coordinates":[5.914728549382142,51.22972050734703]},"properties":{"location_id":59742,"base_color":"#B20A2F","provider_slug":"prorail","bands":["900"],"deleted":false,"is_kpn_huawei":null,"angles":[280.0,90.0]}},{"type":"Feature","geometry":{"type":"Point","coordinates":[4.752778364881828,52.38527609947741]},"properties":{"location_id":59649,"base_color":"#B20A2F","provider_slug":"prorail","bands":["900"],"deleted":false,"is_kpn_huawei":null,"angles":[80.0,265.0]}},{"type":"Feature","geometry":{"type":"Point","coordinates":[4.629168634232661,52.38889047782]},"properties":{"location_id":59651,"base_color":"#B20A2F","provider_slug":"prorail","bands":["900"],"deleted":false,"is_kpn_huawei":null,"angles":[0.0,235.0,95.0]}},{"type":"Feature","geometry":{"type":"Point","coordinates":[4.408607383321991,51.92305381745277]},"properties":{"location_id":59824,"base_color":"#B20A2F","provider_slug":"prorail","bands":["900"],"deleted":false,"is_kpn_huawei":null,"angles":[105.0,265.0,335.0]}},{"type":"Feature","geometry":{"type":"Point","coordinates":[5.142215925311514,52.11388804490604]},"properties":{"location_id":60530,"base_color":"#B20A2F","provider_slug":"prorail","bands":["900"],"deleted":false,"is_kpn_huawei":null,"angles":[65.0,185.0,245.0,15.0]}}]}